cosCU.v
// controller unit module for cos (state machine)
module cosCU (input clk, rst, start, cnt8,
  output reg done, ldX, initT1, initC1, ldT, ldC, init0, cntUp, selXR);

  // states
  reg [2:0] pstate, nstate;
  parameter IDLE = 0, STARTING = 1, GETINPUT = 2, MULT1 = 3,  MULT2 = 4, ADD = 5;

  // registers
  always @(posedge clk, posedge rst) begin
    if (rst == 1)
      pstate <= IDLE;
    else
      pstate <= nstate;
  end

  // combinational part
  always @(pstate, start, cnt8) begin
    nstate = IDLE; // default
    done = 0;
    {ldX, initT1, initC1, ldT, ldC, init0, cntUp, selXR} = 8'b0;
    // 1. State: IDLE
    if (pstate == IDLE) begin nstate = (start == 1) ? STARTING : IDLE;
      done = 1;
    end
    // 2. State: STARTING
    if (pstate == STARTING) begin 
      nstate = (start == 0) ? GETINPUT: STARTING;
    end
    // 3. State: GETINPUT
    if (pstate == GETINPUT) begin 
      nstate = MULT1;
      ldX = 1; initT1 = 1; initC1 = 1; init0 = 1;
    end
    // 4. State: MULT1
    if (pstate == MULT1) begin 
      nstate = MULT2;
      selXR = 1; ldT = 1;
    end
    // 5. State: MULT2
    if (pstate == MULT2) begin 
      nstate = ADD;
      ldT = 1;
    end
    // 6. State: ADD 
    if (pstate == ADD) begin 
      nstate = (cnt8 == 1)? IDLE : MULT1;
      ldC = 1; cntUp = 1;
    end
  end

endmodule

reg18.v
// 18 bit registers for output busses
module reg18 (input clk, rst, init1, load, input [17:0] in, output reg [17:0] out);
  always @ (posedge clk, posedge rst) begin
    if (rst == 1)
      out <= 0;
    else begin
      if (init1 == 1)
        out <= {2'b01, 16'h0000};
      else begin
        if (load == 1)
          out <= in;
      end
    end
  end
endmodule

reg16.v
// 16 bit registers for input busses
module reg16 (input clk, rst, init1, load, input [15:0] in, output reg [15:0] out);
  always @ (posedge clk, posedge rst) begin
    if (rst == 1)
      out <= 0;
    else begin
      if (init1 == 1)
        out <= 16'hFFFF;
      else begin
        if (load == 1)
          out <= in;
      end
    end
  end
endmodule

cosLUT.v
// look up table module for cos 
module cosLUT (input [2:0]addr, output [15:0] data);
  reg [15:0] dataOut;
  always @(addr) begin
    case(addr)
      0: dataOut = 16'h8000; // 1/2!
      1: dataOut = 16'h0AAB; // 1/4!
      2: dataOut = 16'h005B; // 1/6!
      3: dataOut = 16'h0002; // 1/8!
      4: dataOut = 16'h0000; // 1/10! ~= 0
      5: dataOut = 16'h0000; // 1/12! ~= 0
      6: dataOut = 16'h0000; // 1/14! ~= 0
      7: dataOut = 16'h0000; // 1/16! ~= 0
    endcase
  end
  assign data = dataOut;
endmodule

cntReg.v
// 3-bit counter module
module cntReg (input clk, rst, cntUp, init0, output reg [2:0] cnt);
  always @ (posedge clk, posedge rst) begin
    if (rst == 1)
      cnt <= 0;
    else begin
      if (init0 == 1)
        cnt <= 0;
      else begin
        if (cntUp == 1)
          cnt <= cnt + 1;
      end
    end
  end
endmodule

cosDU.v
// datapath module for sin 
module cosDU (input clk, rst, cntUp, init0, ldX, ldT, initT1, ldC, initC1, selXR,
  input [15:0] xBus, output cnt8, output [17:0] rBus);

  // mid-level signals
  wire [2:0] cntOut;
  wire [17:0] cOut, addOut;
  wire [15:0] lutOut, xOut, tOut, muxOut;
  wire [31:0] mulOut;
  wire isOdd;
  wire [31:0] xSquared;

  // module instantiations 
  cntReg cntr(clk, rst, cntUp, init0, cntOut);
  cosLUT lut(cntOut, lutOut);
  reg16 xReg(clk, rst, 1'b0, ldX, xBus, xOut); // no need to initialize
  reg16 tReg(clk, rst, initT1, ldT, mulOut[31:16], tOut); // back to exp style (init to 1)
  reg18 cReg(clk, rst, initC1, ldC, addOut, cOut); // back to exp style

  // add sub assignment: if it's odd cntOut[0] would be 1
  assign isOdd = cntOut[0]; // new

  // output assigning
  assign xSquared = xOut * xOut; // new
  assign muxOut = (selXR == 0) ? xSquared[31:16] : lutOut; // mux
  assign mulOut = (muxOut * tOut); 
  assign addOut = (isOdd == 1) ? cOut - {2'b00, tOut} : cOut + {2'b00, tOut}; // new

  // final output
  assign rBus = cOut;
  assign cnt8 = (cntOut == 3'b111) ? 1 : 0;

endmodule

cosTop.v
// top module for cos 
module cosTop (input clk, rst, start, input [15:0] xBus, output [17:0] rBus, output done);
  // 1-bit wires 
  wire cntUp, init0, ldX, ldT, initT1, initC1, selXR, cnt8;

  // datapath
  cosDU du(clk, rst, cntUp, init0, ldX, ldT, initT1, ldC, initC1, selXR, xBus, cnt8, rBus);

  // controller
  cosCU cp(clk, rst, start, cnt8, done, ldX, initT1, initC1, ldT, ldC, init0, cntUp, selXR);

endmodule

cosTB.v
// test bech for cos module
`timescale 1ns/1ns

module cosTB ();
  reg clk = 0;
  reg rst = 0;
  reg start = 0;
  reg [15:0] xBus;
  wire done;
  wire [17:0] rBus;

  cosTop cos(clk, rst, start, xBus, rBus, done);

  // generating clock behaviour
  always #5 clk <= ~clk;
  initial begin
    // Dump waveform data to a file.
    $dumpfile("cos_sim.vcd");
    $dumpvars(0, cosTB);

    // x = 0 rad => cos(x) = 1.0 rad
    #5;
    rst = 1;

    #5;
    #5;
    rst = 0;
    xBus = 0;
    start = 1;

    #5;
    #5;
    start = 0;

    #300;

    // x = 0.125 rad => cos(x) = 0.992197 rad
    #5;
    rst = 1;

    #5;
    #5;
    rst = 0;
    xBus = 16'h2000; // 0.125
    start = 1;

    #5;
    #5;
    start = 0;

    #300;

    // x = 0.25 rad => cos(x) = 0.96891 rad
    #5;
    rst = 1;

    #5;
    #5;
    rst = 0;
    xBus = 16'h4000; // 0.25
    start = 1;

    #5;
    #5;
    start = 0;

    #300;
    // x = 0.5 rad => cos(x) = 0.877582 rad
    #5;
    rst = 1;

    #5;
    #5;
    rst = 0;
    xBus = 16'h8000; // 0.5
    start = 1;

    #5;
    #5;
    start = 0;

    #300;
    // x = 1 rad => cos(x) = 0.54030 rad
    #5;
    rst = 1;

    #5;
    #5;
    rst = 0;
    xBus = 16'hFFFF; // 1 
    start = 1;

    #5;
    #5;
    start = 0;

    #300;

    // x = 1.5 rad => cos(x) ≈ 0.07074
    #5; rst = 1;
    #5; #5; rst = 0; xBus = 16'h18000; start = 1;
    #5; #5; start = 0;
    #300;

    // x = 2 rad => cos(x) ≈ -0.41615
    #5; rst = 1;
    #5; #5; rst = 0; xBus = 16'h20000; start = 1;
    #5; #5; start = 0;
    #300;

    // x = 2.5 rad => cos(x) ≈ -0.80114
    #5; rst = 1;
    #5; #5; rst = 0; xBus = 16'h28000; start = 1;
    #5; #5; start = 0;
    #300;

    // x = 3 rad => cos(x) ≈ -0.98999
    #5; rst = 1;
    #5; #5; rst = 0; xBus = 16'h30000; start = 1;
    #5; #5; start = 0;
    #300;

    // x = 3.5 rad => cos(x) ≈ -0.93646
    #5; rst = 1;
    #5; #5; rst = 0; xBus = 16'h38000; start = 1;
    #5; #5; start = 0;
    #300;

    $finish; 
  end

endmodule

cos_sim.vcd
$date
	Fri Feb  7 14:52:00 2025
$end
$version
	Icarus Verilog
$end
$timescale
	1ns
$end
$scope module cosTB $end
$var wire 18 ! rBus [17:0] $end
$var wire 1 " done $end
$var reg 1 # clk $end
$var reg 1 $ rst $end
$var reg 1 % start $end
$var reg 16 & xBus [15:0] $end
$scope module cos $end
$var wire 1 # clk $end
$var wire 1 $ rst $end
$var wire 1 % start $end
$var wire 16 ' xBus [15:0] $end
$var wire 1 ( selXR $end
$var wire 18 ) rBus [17:0] $end
$var wire 1 * ldX $end
$var wire 1 + ldT $end
$var wire 1 , ldC $end
$var wire 1 - initT1 $end
$var wire 1 . initC1 $end
$var wire 1 / init0 $end
$var wire 1 " done $end
$var wire 1 0 cntUp $end
$var wire 1 1 cnt8 $end
$scope module cp $end
$var wire 1 # clk $end
$var wire 1 $ rst $end
$var wire 1 % start $end
$var wire 1 1 cnt8 $end
$var parameter 32 2 ADD $end
$var parameter 32 3 GETINPUT $end
$var parameter 32 4 IDLE $end
$var parameter 32 5 MULT1 $end
$var parameter 32 6 MULT2 $end
$var parameter 32 7 STARTING $end
$var reg 1 0 cntUp $end
$var reg 1 " done $end
$var reg 1 / init0 $end
$var reg 1 . initC1 $end
$var reg 1 - initT1 $end
$var reg 1 , ldC $end
$var reg 1 + ldT $end
$var reg 1 * ldX $end
$var reg 3 8 nstate [2:0] $end
$var reg 3 9 pstate [2:0] $end
$var reg 1 ( selXR $end
$upscope $end
$scope module du $end
$var wire 1 # clk $end
$var wire 1 0 cntUp $end
$var wire 1 / init0 $end
$var wire 1 . initC1 $end
$var wire 1 - initT1 $end
$var wire 1 , ldC $end
$var wire 1 + ldT $end
$var wire 1 * ldX $end
$var wire 18 : rBus [17:0] $end
$var wire 1 $ rst $end
$var wire 1 ( selXR $end
$var wire 16 ; xBus [15:0] $end
$var wire 32 < xSquared [31:0] $end
$var wire 16 = xOut [15:0] $end
$var wire 16 > tOut [15:0] $end
$var wire 16 ? muxOut [15:0] $end
$var wire 32 @ mulOut [31:0] $end
$var wire 16 A lutOut [15:0] $end
$var wire 1 B isOdd $end
$var wire 3 C cntOut [2:0] $end
$var wire 1 1 cnt8 $end
$var wire 18 D cOut [17:0] $end
$var wire 18 E addOut [17:0] $end
$scope module cReg $end
$var wire 1 # clk $end
$var wire 18 F in [17:0] $end
$var wire 1 . init1 $end
$var wire 1 , load $end
$var wire 1 $ rst $end
$var reg 18 G out [17:0] $end
$upscope $end
$scope module cntr $end
$var wire 1 # clk $end
$var wire 1 0 cntUp $end
$var wire 1 / init0 $end
$var wire 1 $ rst $end
$var reg 3 H cnt [2:0] $end
$upscope $end
$scope module lut $end
$var wire 3 I addr [2:0] $end
$var wire 16 J data [15:0] $end
$var reg 16 K dataOut [15:0] $end
$upscope $end
$scope module tReg $end
$var wire 1 # clk $end
$var wire 16 L in [15:0] $end
$var wire 1 - init1 $end
$var wire 1 + load $end
$var wire 1 $ rst $end
$var reg 16 M out [15:0] $end
$upscope $end
$scope module xReg $end
$var wire 1 # clk $end
$var wire 16 N in [15:0] $end
$var wire 1 O init1 $end
$var wire 1 * load $end
$var wire 1 $ rst $end
$var reg 16 P out [15:0] $end
$upscope $end
$upscope $end
$upscope $end
$upscope $end
$enddefinitions $end
$comment Show the parameter values. $end
$dumpall
b1 7
b100 6
b11 5
b0 4
b10 3
b101 2
$end
#0
$dumpvars
bx P
0O
bx N
bx M
bx L
bx K
bx J
bx I
bx H
bx G
bx F
bx E
bx D
bx C
xB
bx A
bx @
bx ?
bx >
bx =
bx <
bx ;
bx :
bx 9
b0 8
x1
00
0/
0.
0-
0,
0+
0*
bx )
0(
bx '
bx &
0%
0$
0#
0"
bx !
$end
#5
b0 L
01
b0 @
b0 ?
b1000000000000000 A
b1000000000000000 J
b1000000000000000 K
0B
b0 E
b0 F
1"
b0 C
b0 H
b0 I
b0 <
b0 =
b0 P
b0 >
b0 M
b0 !
b0 )
b0 :
b0 D
b0 G
b0 9
1#
1$
#10
0#
#15
b1 9
1#
b1 8
0"
1%
b0 &
b0 '
b0 ;
b0 N
0$
#20
0#
#25
1/
1.
1-
1*
b10 9
1#
b11 8
0%
#30
0#
#35
b111111111111111 L
b1111111111111111000000000000000 @
b1000000000000000 ?
b11111111111111111 E
b11111111111111111 F
1+
1(
0*
0-
0.
0/
b100 8
b1111111111111111 >
b1111111111111111 M
b10000000000000000 !
b10000000000000000 )
b10000000000000000 :
b10000000000000000 D
b10000000000000000 G
b11 9
1#
#40
0#
#45
b0 ?
1+
0(
b101 8
b10111111111111111 E
b10111111111111111 F
b0 L
b100 9
b0 @
b111111111111111 >
b111111111111111 M
1#
#50
0#
#55
b10000000000000000 E
b10000000000000000 F
10
1,
0+
b11 8
b0 >
b0 M
b101 9
1#
#60
0#
#65
b101010101011 ?
1+
1(
0,
00
b100 8
b101010101011 A
b101010101011 J
b101010101011 K
1B
b11 9
b1 C
b1 H
b1 I
1#
#70
0#
#75
b0 ?
1+
0(
b101 8
b100 9
1#
#80
0#
#85
10
1,
0+
b11 8
b101 9
1#
#90
0#
#95
b1011011 ?
b1011011 A
b1011011 J
b1011011 K
0B
1+
1(
0,
00
b100 8
b10 C
b10 H
b10 I
b11 9
1#
#100
0#
#105
b0 ?
1+
0(
b101 8
b100 9
1#
#110
0#
#115
10
1,
0+
b11 8
b101 9
1#
#120
0#
#125
b10 ?
1+
1(
0,
00
b100 8
b10 A
b10 J
b10 K
1B
b11 9
b11 C
b11 H
b11 I
1#
#130
0#
#135
b0 ?
1+
0(
b101 8
b100 9
1#
#140
0#
#145
10
1,
0+
b11 8
b101 9
1#
#150
0#
#155
b0 A
b0 J
b0 K
0B
1+
1(
0,
00
b100 8
b100 C
b100 H
b100 I
b11 9
1#
#160
0#
#165
1+
0(
b101 8
b100 9
1#
#170
0#
#175
10
1,
0+
b11 8
b101 9
1#
#180
0#
#185
1+
1(
0,
00
b100 8
1B
b11 9
b101 C
b101 H
b101 I
1#
#190
0#
#195
1+
0(
b101 8
b100 9
1#
#200
0#
#205
10
1,
0+
b11 8
b101 9
1#
#210
0#
#215
0B
1+
1(
0,
00
b100 8
b110 C
b110 H
b110 I
b11 9
1#
#220
0#
#225
1+
0(
b101 8
b100 9
1#
#230
0#
#235
10
1,
0+
b11 8
b101 9
1#
#240
0#
#245
11
1+
1(
0,
00
b100 8
1B
b11 9
b111 C
b111 H
b111 I
1#
#250
0#
#255
1+
0(
b101 8
b100 9
1#
#260
0#
#265
10
1,
0+
b0 8
b101 9
1#
#270
0#
#275
01
b1000000000000000 A
b1000000000000000 J
b1000000000000000 K
0B
1"
0,
00
b0 C
b0 H
b0 I
b0 9
1#
#280
0#
#285
1#
#290
0#
#295
1#
#300
0#
#305
1#
#310
0#
#315
1#
#320
0#
#325
1#
#330
b0 E
b0 F
b0 !
b0 )
b0 :
b0 D
b0 G
0#
1$
#335
1#
#340
0#
b1 8
1"
1%
b10000000000000 &
b10000000000000 '
b10000000000000 ;
b10000000000000 N
0$
#345
0"
b1 8
b1 9
1#
#350
0#
b10 8
0%
#355
1/
1.
1-
1*
b11 8
b10 9
1#
#360
0#
#365
b111111111111111 L
b1111111111111111000000000000000 @
b1000000000000000 ?
b11111111111111111 E
b11111111111111111 F
1+
1(
0*
0-
0.
0/
b100 8
b100000000000000000000000000 <
b10000000000000 =
b10000000000000 P
b1111111111111111 >
b1111111111111111 M
b10000000000000000 !
b10000000000000000 )
b10000000000000000 :
b10000000000000000 D
b10000000000000000 G
b11 9
1#
#370
0#
#375
b10000000000 ?
1+
0(
b101 8
b10111111111111111 E
b10111111111111111 F
b111111111 L
b100 9
b1111111111111110000000000 @
b111111111111111 >
b111111111111111 M
1#
#380
0#
#385
b10000000111111111 E
b10000000111111111 F
b111 L
10
1,
0+
b11 8
b1111111110000000000 @
b111111111 >
b111111111 M
b101 9
1#
#390
0#
#395
b10101 L
b101010100101101010101 @
b101010101011 ?
1+
1(
0,
00
b100 8
b10000000000000000 E
b10000000000000000 F
b101010101011 A
b101010101011 J
b101010101011 K
1B
b11 9
b10000000111111111 !
b10000000111111111 )
b10000000111111111 :
b10000000111111111 D
b10000000111111111 G
b1 C
b1 H
b1 I
1#
#400
0#
#405
b10000000000 ?
b10000000111101010 E
b10000000111101010 F
b0 L
1+
0(
b101 8
b101010000000000 @
b10101 >
b10101 M
b100 9
1#
#410
0#
#415
10
1,
0+
b11 8
b10000000111111111 E
b10000000111111111 F
b101 9
b0 @
b0 >
b0 M
1#
#420
0#
#425
b1011011 ?
b1011011 A
b1011011 J
b1011011 K
0B
1+
1(
0,
00
b100 8
b10 C
b10 H
b10 I
b11 9
1#
#430
0#
#435
b10000000000 ?
1+
0(
b101 8
b100 9
1#
#440
0#
#445
10
1,
0+
b11 8
b101 9
1#
#450
0#
#455
b10 ?
1+
1(
0,
00
b100 8
b10 A
b10 J
b10 K
1B
b11 9
b11 C
b11 H
b11 I
1#
#460
0#
#465
b10000000000 ?
1+
0(
b101 8
b100 9
1#
#470
0#
#475
10
1,
0+
b11 8
b101 9
1#
#480
0#
#485
b0 ?
b0 A
b0 J
b0 K
0B
1+
1(
0,
00
b100 8
b100 C
b100 H
b100 I
b11 9
1#
#490
0#
#495
b10000000000 ?
1+
0(
b101 8
b100 9
1#
#500
0#
#505
10
1,
0+
b11 8
b101 9
1#
#510
0#
#515
b0 ?
1+
1(
0,
00
b100 8
1B
b11 9
b101 C
b101 H
b101 I
1#
#520
0#
#525
b10000000000 ?
1+
0(
b101 8
b100 9
1#
#530
0#
#535
10
1,
0+
b11 8
b101 9
1#
#540
0#
#545
b0 ?
0B
1+
1(
0,
00
b100 8
b110 C
b110 H
b110 I
b11 9
1#
#550
0#
#555
b10000000000 ?
1+
0(
b101 8
b100 9
1#
#560
0#
#565
10
1,
0+
b11 8
b101 9
1#
#570
0#
#575
b0 ?
11
1+
1(
0,
00
b100 8
1B
b11 9
b111 C
b111 H
b111 I
1#
#580
0#
#585
b10000000000 ?
1+
0(
b101 8
b100 9
1#
#590
0#
#595
10
1,
0+
b0 8
b101 9
1#
#600
0#
#605
01
b1000000000000000 A
b1000000000000000 J
b1000000000000000 K
0B
1"
0,
00
b0 C
b0 H
b0 I
b0 9
1#
#610
0#
#615
1#
#620
0#
#625
1#
#630
0#
#635
1#
#640
0#
#645
1#
#650
0#
#655
b0 ?
b0 E
b0 F
b0 !
b0 )
b0 :
b0 D
b0 G
b0 <
b0 =
b0 P
1#
1$
#660
0#
#665
b1 9
1#
b1 8
0"
1%
b100000000000000 &
b100000000000000 '
b100000000000000 ;
b100000000000000 N
0$
#670
0#
#675
1/
1.
1-
1*
b10 9
1#
b11 8
0%
#680
0#
#685
b111111111111111 L
b1111111111111111000000000000000 @
b1000000000000000 ?
1+
1(
0*
0-
0.
0/
b100 8
b11111111111111111 E
b11111111111111111 F
b11 9
b10000000000000000 !
b10000000000000000 )
b10000000000000000 :
b10000000000000000 D
b10000000000000000 G
b1111111111111111 >
b1111111111111111 M
b10000000000000000000000000000 <
b100000000000000 =
b100000000000000 P
1#
#690
0#
#695
b1000000000000 ?
b10111111111111111 E
b10111111111111111 F
b11111111111 L
1+
0(
b101 8
b111111111111111000000000000 @
b111111111111111 >
b111111111111111 M
b100 9
1#
#700
0#
#705
10
1,
0+
b11 8
b10000011111111111 E
b10000011111111111 F
b1111111 L
b101 9
b11111111111000000000000 @
b11111111111 >
b11111111111 M
1#
#710
0#
#715
b1010101 L
b10101010100110101010101 @
b101010101011 ?
b101010101011 A
b101010101011 J
b101010101011 K
1B
b10000000000000000 E
b10000000000000000 F
1+
1(
0,
00
b100 8
b1 C
b1 H
b1 I
b10000011111111111 !
b10000011111111111 )
b10000011111111111 :
b10000011111111111 D
b10000011111111111 G
b11 9
1#
#720
0#
#725
b1000000000000 ?
1+
0(
b101 8
b10000011110101010 E
b10000011110101010 F
b101 L
b100 9
b1010101000000000000 @
b1010101 >
b1010101 M
1#
#730
0#
#735
b10000011111111010 E
b10000011111111010 F
b0 L
10
1,
0+
b11 8
b101000000000000 @
b101 >
b101 M
b101 9
1#
#740
0#
#745
b111000111 @
b1011011 ?
1+
1(
0,
00
b100 8
b10000011111111111 E
b10000011111111111 F
b1011011 A
b1011011 J
b1011011 K
0B
b11 9
b10000011111111010 !
b10000011111111010 )
b10000011111111010 :
b10000011111111010 D
b10000011111111010 G
b10 C
b10 H
b10 I
1#
#750
0#
#755
b1000000000000 ?
b10000011111111010 E
b10000011111111010 F
1+
0(
b101 8
b0 @
b0 >
b0 M
b100 9
1#
#760
0#
#765
10
1,
0+
b11 8
b101 9
1#
#770
0#
#775
b10 ?
b10 A
b10 J
b10 K
1B
1+
1(
0,
00
b100 8
b11 C
b11 H
b11 I
b11 9
1#
#780
0#
#785
b1000000000000 ?
1+
0(
b101 8
b100 9
1#
#790
0#
#795
10
1,
0+
b11 8
b101 9
1#
#800
0#
#805
b0 ?
1+
1(
0,
00
b100 8
b0 A
b0 J
b0 K
0B
b11 9
b100 C
b100 H
b100 I
1#
#810
0#
#815
b1000000000000 ?
1+
0(
b101 8
b100 9
1#
#820
0#
#825
10
1,
0+
b11 8
b101 9
1#
#830
0#
#835
b0 ?
1B
1+
1(
0,
00
b100 8
b101 C
b101 H
b101 I
b11 9
1#
#840
0#
#845
b1000000000000 ?
1+
0(
b101 8
b100 9
1#
#850
0#
#855
10
1,
0+
b11 8
b101 9
1#
#860
0#
#865
b0 ?
1+
1(
0,
00
b100 8
0B
b11 9
b110 C
b110 H
b110 I
1#
#870
0#
#875
b1000000000000 ?
1+
0(
b101 8
b100 9
1#
#880
0#
#885
10
1,
0+
b11 8
b101 9
1#
#890
0#
#895
11
b0 ?
1B
1+
1(
0,
00
b100 8
b111 C
b111 H
b111 I
b11 9
1#
#900
0#
#905
b1000000000000 ?
1+
0(
b101 8
b100 9
1#
#910
0#
#915
10
1,
0+
b0 8
b101 9
1#
#920
0#
#925
01
1"
0,
00
b1000000000000000 A
b1000000000000000 J
b1000000000000000 K
0B
b0 9
b0 C
b0 H
b0 I
1#
#930
0#
#935
1#
#940
0#
#945
1#
#950
0#
#955
1#
#960
0#
#965
1#
#970
0#
#975
1#
#980
b0 ?
b0 E
b0 F
b0 !
b0 )
b0 :
b0 D
b0 G
b0 <
b0 =
b0 P
0#
1$
#985
1#
#990
0#
b1 8
1"
1%
b1000000000000000 &
b1000000000000000 '
b1000000000000000 ;
b1000000000000000 N
0$
#995
0"
b1 8
b1 9
1#
#1000
0#
b10 8
0%
#1005
1/
1.
1-
1*
b11 8
b10 9
1#
#1010
0#
#1015
b111111111111111 L
b1111111111111111000000000000000 @
b1000000000000000 ?
1+
1(
0*
0-
0.
0/
b100 8
b11111111111111111 E
b11111111111111111 F
b11 9
b10000000000000000 !
b10000000000000000 )
b10000000000000000 :
b10000000000000000 D
b10000000000000000 G
b1111111111111111 >
b1111111111111111 M
b1000000000000000000000000000000 <
b1000000000000000 =
b1000000000000000 P
1#
#1020
0#
#1025
b100000000000000 ?
b10111111111111111 E
b10111111111111111 F
b1111111111111 L
1+
0(
b101 8
b11111111111111100000000000000 @
b111111111111111 >
b111111111111111 M
b100 9
1#
#1030
0#
#1035
10
1,
0+
b11 8
b10001111111111111 E
b10001111111111111 F
b11111111111 L
b101 9
b111111111111100000000000000 @
b1111111111111 >
b1111111111111 M
1#
#1040
0#
#1045
b101010101 L
b1010101010101010101010101 @
b101010101011 ?
b101010101011 A
b101010101011 J
b101010101011 K
1B
b10000000000000000 E
b10000000000000000 F
1+
1(
0,
00
b100 8
b1 C
b1 H
b1 I
b10001111111111111 !
b10001111111111111 )
b10001111111111111 :
b10001111111111111 D
b10001111111111111 G
b11 9
1#
#1050
0#
#1055
b100000000000000 ?
1+
0(
b101 8
b10001111010101010 E
b10001111010101010 F
b1010101 L
b100 9
b10101010100000000000000 @
b101010101 >
b101010101 M
1#
#1060
0#
#1065
b10001111110101010 E
b10001111110101010 F
b10101 L
10
1,
0+
b11 8
b101010100000000000000 @
b1010101 >
b1010101 M
b101 9
1#
#1070
0#
#1075
b0 L
b1111000110111 @
b1011011 ?
1+
1(
0,
00
b100 8
b10001111111111111 E
b10001111111111111 F
b1011011 A
b1011011 J
b1011011 K
0B
b11 9
b10001111110101010 !
b10001111110101010 )
b10001111110101010 :
b10001111110101010 D
b10001111110101010 G
b10 C
b10 H
b10 I
1#
#1080
0#
#1085
b100000000000000 ?
b10001111110101010 E
b10001111110101010 F
1+
0(
b101 8
b0 @
b0 >
b0 M
b100 9
1#
#1090
0#
#1095
10
1,
0+
b11 8
b101 9
1#
#1100
0#
#1105
b10 ?
b10 A
b10 J
b10 K
1B
1+
1(
0,
00
b100 8
b11 C
b11 H
b11 I
b11 9
1#
#1110
0#
#1115
b100000000000000 ?
1+
0(
b101 8
b100 9
1#
#1120
0#
#1125
10
1,
0+
b11 8
b101 9
1#
#1130
0#
#1135
b0 ?
1+
1(
0,
00
b100 8
b0 A
b0 J
b0 K
0B
b11 9
b100 C
b100 H
b100 I
1#
#1140
0#
#1145
b100000000000000 ?
1+
0(
b101 8
b100 9
1#
#1150
0#
#1155
10
1,
0+
b11 8
b101 9
1#
#1160
0#
#1165
b0 ?
1B
1+
1(
0,
00
b100 8
b101 C
b101 H
b101 I
b11 9
1#
#1170
0#
#1175
b100000000000000 ?
1+
0(
b101 8
b100 9
1#
#1180
0#
#1185
10
1,
0+
b11 8
b101 9
1#
#1190
0#
#1195
b0 ?
1+
1(
0,
00
b100 8
0B
b11 9
b110 C
b110 H
b110 I
1#
#1200
0#
#1205
b100000000000000 ?
1+
0(
b101 8
b100 9
1#
#1210
0#
#1215
10
1,
0+
b11 8
b101 9
1#
#1220
0#
#1225
11
b0 ?
1B
1+
1(
0,
00
b100 8
b111 C
b111 H
b111 I
b11 9
1#
#1230
0#
#1235
b100000000000000 ?
1+
0(
b101 8
b100 9
1#
#1240
0#
#1245
10
1,
0+
b0 8
b101 9
1#
#1250
0#
#1255
01
1"
0,
00
b1000000000000000 A
b1000000000000000 J
b1000000000000000 K
0B
b0 9
b0 C
b0 H
b0 I
1#
#1260
0#
#1265
1#
#1270
0#
#1275
1#
#1280
0#
#1285
1#
#1290
0#
#1295
1#
#1300
0#
#1305
b0 ?
b0 E
b0 F
b0 <
b0 =
b0 P
b0 !
b0 )
b0 :
b0 D
b0 G
1#
1$
#1310
0#
#1315
b1 9
1#
b1 8
0"
1%
b1111111111111111 &
b1111111111111111 '
b1111111111111111 ;
b1111111111111111 N
0$
#1320
0#
#1325
1/
1.
1-
1*
b10 9
1#
b11 8
0%
#1330
0#
#1335
b111111111111111 L
b1111111111111111000000000000000 @
b1000000000000000 ?
b11111111111111111 E
b11111111111111111 F
1+
1(
0*
0-
0.
0/
b100 8
b11111111111111100000000000000001 <
b1111111111111111 =
b1111111111111111 P
b1111111111111111 >
b1111111111111111 M
b10000000000000000 !
b10000000000000000 )
b10000000000000000 :
b10000000000000000 D
b10000000000000000 G
b11 9
1#
#1340
0#
#1345
b1111111111111110 ?
1+
0(
b101 8
b10111111111111111 E
b10111111111111111 F
b111111111111110 L
b100 9
b1111111111111100000000000000010 @
b111111111111111 >
b111111111111111 M
1#
#1350
0#
#1355
b10111111111111110 E
b10111111111111110 F
b111111111111101 L
10
1,
0+
b11 8
b1111111111111010000000000000100 @
b111111111111110 >
b111111111111110 M
b101 9
1#
#1360
0#
#1365
b10101010101 L
b101010101010110101010101010 @
b101010101011 ?
1+
1(
0,
00
b100 8
b10000000000000000 E
b10000000000000000 F
b101010101011 A
b101010101011 J
b101010101011 K
1B
b11 9
b10111111111111110 !
b10111111111111110 )
b10111111111111110 :
b10111111111111110 D
b10111111111111110 G
b1 C
b1 H
b1 I
1#
#1370
0#
#1375
b1111111111111110 ?
b10111101010101001 E
b10111101010101001 F
b10101010100 L
1+
0(
b101 8
b101010101001111010101010110 @
b10101010101 >
b10101010101 M
b100 9
1#
#1380
0#
#1385
10
1,
0+
b11 8
b10111101010101010 E
b10111101010101010 F
b10101010011 L
b101 9
b101010100111111010101011000 @
b10101010100 >
b10101010100 M
1#
#1390
0#
#1395
b1 L
b11110010011011100 @
b1011011 ?
b1011011 A
b1011011 J
b1011011 K
0B
b10111111111111110 E
b10111111111111110 F
1+
1(
0,
00
b100 8
b10 C
b10 H
b10 I
b10111101010101010 !
b10111101010101010 )
b10111101010101010 :
b10111101010101010 D
b10111101010101010 G
b11 9
1#
#1400
0#
#1405
b1111111111111110 ?
1+
0(
b101 8
b10111101010101011 E
b10111101010101011 F
b0 L
b100 9
b1111111111111110 @
b1 >
b1 M
1#
#1410
0#
#1415
b10111101010101010 E
b10111101010101010 F
10
1,
0+
b11 8
b0 @
b0 >
b0 M
b101 9
1#
#1420
0#
#1425
b10 ?
1+
1(
0,
00
b100 8
b10 A
b10 J
b10 K
1B
b11 9
b11 C
b11 H
b11 I
1#
#1430
0#
#1435
b1111111111111110 ?
1+
0(
b101 8
b100 9
1#
#1440
0#
#1445
10
1,
0+
b11 8
b101 9
1#
#1450
0#
#1455
b0 ?
b0 A
b0 J
b0 K
0B
1+
1(
0,
00
b100 8
b100 C
b100 H
b100 I
b11 9
1#
#1460
0#
#1465
b1111111111111110 ?
1+
0(
b101 8
b100 9
1#
#1470
0#
#1475
10
1,
0+
b11 8
b101 9
1#
#1480
0#
#1485
b0 ?
1+
1(
0,
00
b100 8
1B
b11 9
b101 C
b101 H
b101 I
1#
#1490
0#
#1495
b1111111111111110 ?
1+
0(
b101 8
b100 9
1#
#1500
0#
#1505
10
1,
0+
b11 8
b101 9
1#
#1510
0#
#1515
b0 ?
0B
1+
1(
0,
00
b100 8
b110 C
b110 H
b110 I
b11 9
1#
#1520
0#
#1525
b1111111111111110 ?
1+
0(
b101 8
b100 9
1#
#1530
0#
#1535
10
1,
0+
b11 8
b101 9
1#
#1540
0#
#1545
b0 ?
11
1+
1(
0,
00
b100 8
1B
b11 9
b111 C
b111 H
b111 I
1#
#1550
0#
#1555
b1111111111111110 ?
1+
0(
b101 8
b100 9
1#
#1560
0#
#1565
10
1,
0+
b0 8
b101 9
1#
#1570
0#
#1575
01
b1000000000000000 A
b1000000000000000 J
b1000000000000000 K
0B
1"
0,
00
b0 C
b0 H
b0 I
b0 9
1#
#1580
0#
#1585
1#
#1590
0#
#1595
1#
#1600
0#
#1605
1#
#1610
0#
#1615
1#
#1620
0#
#1625
1#
#1630
b0 ?
b0 E
b0 F
b0 <
b0 =
b0 P
b0 !
b0 )
b0 :
b0 D
b0 G
0#
1$
#1635
1#
#1640
0#
b1 8
1"
1%
b1000000000000000 &
b1000000000000000 '
b1000000000000000 ;
b1000000000000000 N
0$
#1645
0"
b1 8
b1 9
1#
#1650
0#
b10 8
0%
#1655
1/
1.
1-
1*
b11 8
b10 9
1#
#1660
0#
