expCU.v
// controller unit module for exponential (state machine)
module expCU (input clk, rst, start, cnt8,
  output reg done, ldX, initT1, initE1, ldT, ldE, init0, cntUp, selXR);

  // states
  reg [2:0] pstate, nstate;
  parameter IDLE = 0, STARTING = 1, GETINPUT = 2, MULT1 = 3,  MULT2 = 4, ADD = 5;

  // registers
  always @(posedge clk, posedge rst) begin
    if (rst == 1)
      pstate <= IDLE;
    else
      pstate <= nstate;
  end

  // combinational part
  always @(pstate, start, cnt8) begin
    nstate = IDLE; // default
    done = 0;
    {ldX, initT1, initE1, ldT, ldE, init0, cntUp, selXR} = 8'b0;
    // 1. State: IDLE
    if (pstate == IDLE) begin nstate = (start == 1) ? STARTING : IDLE;
      done = 1;
    end
    // 2. State: STARTING
    if (pstate == STARTING) begin 
      nstate = (start == 0) ? GETINPUT: STARTING;
    end
    // 3. State: GETINPUT
    if (pstate == GETINPUT) begin 
      nstate = MULT1;
      ldX = 1; initT1 = 1; initE1 = 1; init0 = 1;
    end
    // 4. State: MULT1
    if (pstate == MULT1) begin 
      nstate = MULT2;
      selXR = 1; ldT = 1;
    end
    // 5. State: MULT2
    if (pstate == MULT2) begin 
      nstate = ADD;
      ldT = 1;
    end
    // 6. State: ADD 
    if (pstate == ADD) begin 
      nstate = (cnt8 == 1)? IDLE : MULT1;
      ldE = 1; cntUp = 1;
    end
  end

endmodule

reg18.v
// 18 bit registers for output busses
module reg18 (input clk, rst, init1, load, input [17:0] in, output reg [17:0] out);
  always @ (posedge clk, posedge rst) begin
    if (rst == 1)
      out <= 0;
    else begin
      if (init1 == 1)
        out <= {2'b01, 16'h0000};
      else begin
        if (load == 1)
          out <= in;
      end
    end
  end
endmodule

reg16.v
// 16 bit registers for input busses
module reg16 (input clk, rst, init1, load, input [15:0] in, output reg [15:0] out);
  always @ (posedge clk, posedge rst) begin
    if (rst == 1)
      out <= 0;
    else begin
      if (init1 == 1)
        out <= 16'hFFFF;
      else begin
        if (load == 1)
          out <= in;
      end
    end
  end
endmodule

expLUT.v
// look up table module for exponential
module expLUT (input [2:0]addr, output [15:0] data);
  reg [15:0] dataOut;
  always @(addr) begin
    case(addr)
      0: dataOut = 16'hFFFF; // 1/1!
      1: dataOut = 16'h8000; // 1/2!
      2: dataOut = 16'h2AAB; // 1/3!
      3: dataOut = 16'h0AAB; // 1/4!
      4: dataOut = 16'h0222; // 1/5!
      5: dataOut = 16'h005B; // 1/6!
      6: dataOut = 16'h000D; // 1/7!
      7: dataOut = 16'h0002; // 1/8!
    endcase
  end
  assign data = dataOut;
endmodule

cntReg.v
// 3-bit counter module
module cntReg (input clk, rst, cntUp, init0, output reg [2:0] cnt);
  always @ (posedge clk, posedge rst) begin
    if (rst == 1)
      cnt <= 0;
    else begin
      if (init0 == 1)
        cnt <= 0;
      else begin
        if (cntUp == 1)
          cnt <= cnt + 1;
      end
    end
  end
endmodule

expDU.v
// datapath module for exponential
module expDU (input clk, rst, cntUp, init0, ldX, ldT, initT1, ldE, initE1, selXR,
  input [15:0] xBus, output cnt8, output [17:0] rBus);

  // mid-level signals
  wire [2:0] cntOut;
  wire [17:0] eOut, addOut;
  wire [15:0] lutOut, xOut, tOut, muxOut;
  wire [31:0] mulOut;

  // module instantiations 
  cntReg cntr(clk, rst, cntUp, init0, cntOut);
  expLUT lut(cntOut, lutOut);
  reg16 xReg(clk, rst, 1'b0, ldX, xBus, xOut); // no need to initialize
  reg16 tReg(clk, rst, initT1, ldT, mulOut[31:16], tOut);
  reg18 eReg(clk, rst, initE1, ldE, addOut, eOut);

  // output assigning
  assign muxOut = (selXR == 1) ? xOut: lutOut; // mux
  assign addOut = eOut + {2'b00, tOut};
  assign mulOut = (muxOut * tOut); 

  // final output
  assign rBus = eOut;
  assign cnt8 = (cntOut == 3'b111) ? 1 : 0;

endmodule

expTop.v
// top module for exponential
module expTop (input clk, rst, start, input [15:0] xBus, output [17:0] rBus, output done);
  // 1-bit wires 
  wire cntUp, init0, ldX, ldT, initT1, initE1, selXR, cnt8;

  // datapath
  expDU du(clk, rst, cntUp, init0, ldX, ldT, initT1, ldE, initE1, selXR, xBus, cnt8, rBus);

  // controller
  expCU cp(clk, rst, start, cnt8, done, ldX, initT1, initE1, ldT, ldE, init0, cntUp, selXR);

endmodule

expTB.v
// test bech for exponential module
`timescale 1ns/1ns

module expTB ();
  reg clk = 0;
  reg rst = 0;
  reg start = 0;
  reg [15:0] xBus;
  wire done;
  wire [17:0] rBus;

  expTop exp(clk, rst, start, xBus, rBus, done);

  // generating clock behaviour
  always #5 clk <= ~clk;
  initial begin
    // Dump waveform data to a file.
    $dumpfile("exp_sim.vcd");
    $dumpvars(0, expTB);

    // x = 0 => e^x = 1.0
    #5;
    rst = 1;

    #5;
    #5;
    rst = 0;
    xBus = 0;
    start = 1;

    #5;
    #5;
    start = 0;

    #300;

    // x = 0.125 => e^x = 1.1331
    #5;
    rst = 1;

    #5;
    #5;
    rst = 0;
    xBus = 16'h2000; // 0.125
    start = 1;

    #5;
    #5;
    start = 0;

    #300;

    // x = 0.25 => e^x = 1.2840
    #5;
    rst = 1;

    #5;
    #5;
    rst = 0;
    xBus = 16'h4000; // 0.25
    start = 1;

    #5;
    #5;
    start = 0;

    #300;
    // x = 0.5 => e^x = 1.6487
    #5;
    rst = 1;

    #5;
    #5;
    rst = 0;
    xBus = 16'h8000; // 0.5
    start = 1;

    #5;
    #5;
    start = 0;

    #300;
    // x = 1 => e^x = 2.7183
    #5;
    rst = 1;

    #5;
    #5;
    rst = 0;
    xBus = 16'hFFFF; // 1 
    start = 1;

    #5;
    #5;
    start = 0;

    #300;

    // x = 1.5 => e^1.5 ≈ 4.4817
    #5; rst = 1;
    #5; #5; rst = 0; xBus = 16'h18000; start = 1;
    #5; #5; start = 0;
    #300;

    // x = 2 => e^2 ≈ 7.3891
    #5; rst = 1;
    #5; #5; rst = 0; xBus = 16'h20000; start = 1;
    #5; #5; start = 0;
    #300;

    // x = 2.5 => e^2.5 ≈ 12.1825
    #5; rst = 1;
    #5; #5; rst = 0; xBus = 16'h28000; start = 1;
    #5; #5; start = 0;
    #300;

    // x = 3 => e^3 ≈ 20.0855
    #5; rst = 1;
    #5; #5; rst = 0; xBus = 16'h30000; start = 1;
    #5; #5; start = 0;
    #300;

    // x = 3.5 => e^3.5 ≈ 33.1155
    #5; rst = 1;
    #5; #5; rst = 0; xBus = 16'h38000; start = 1;
    #5; #5; start = 0;
    #300;

    $finish; 
  end

endmodule

exp_sim.vcd
$date
	Fri Feb  7 14:44:08 2025
$end
$version
	Icarus Verilog
$end
$timescale
	1ns
$end
$scope module expTB $end
$var wire 18 ! rBus [17:0] $end
$var wire 1 " done $end
$var reg 1 # clk $end
$var reg 1 $ rst $end
$var reg 1 % start $end
$var reg 16 & xBus [15:0] $end
$scope module exp $end
$var wire 1 # clk $end
$var wire 1 $ rst $end
$var wire 1 % start $end
$var wire 16 ' xBus [15:0] $end
$var wire 1 ( selXR $end
$var wire 18 ) rBus [17:0] $end
$var wire 1 * ldX $end
$var wire 1 + ldT $end
$var wire 1 , ldE $end
$var wire 1 - initT1 $end
$var wire 1 . initE1 $end
$var wire 1 / init0 $end
$var wire 1 " done $end
$var wire 1 0 cntUp $end
$var wire 1 1 cnt8 $end
$scope module cp $end
$var wire 1 # clk $end
$var wire 1 $ rst $end
$var wire 1 % start $end
$var wire 1 1 cnt8 $end
$var parameter 32 2 ADD $end
$var parameter 32 3 GETINPUT $end
$var parameter 32 4 IDLE $end
$var parameter 32 5 MULT1 $end
$var parameter 32 6 MULT2 $end
$var parameter 32 7 STARTING $end
$var reg 1 0 cntUp $end
$var reg 1 " done $end
$var reg 1 / init0 $end
$var reg 1 . initE1 $end
$var reg 1 - initT1 $end
$var reg 1 , ldE $end
$var reg 1 + ldT $end
$var reg 1 * ldX $end
$var reg 3 8 nstate [2:0] $end
$var reg 3 9 pstate [2:0] $end
$var reg 1 ( selXR $end
$upscope $end
$scope module du $end
$var wire 1 # clk $end
$var wire 1 0 cntUp $end
$var wire 1 / init0 $end
$var wire 1 . initE1 $end
$var wire 1 - initT1 $end
$var wire 1 , ldE $end
$var wire 1 + ldT $end
$var wire 1 * ldX $end
$var wire 18 : rBus [17:0] $end
$var wire 1 $ rst $end
$var wire 1 ( selXR $end
$var wire 16 ; xBus [15:0] $end
$var wire 16 < xOut [15:0] $end
$var wire 16 = tOut [15:0] $end
$var wire 16 > muxOut [15:0] $end
$var wire 32 ? mulOut [31:0] $end
$var wire 16 @ lutOut [15:0] $end
$var wire 18 A eOut [17:0] $end
$var wire 3 B cntOut [2:0] $end
$var wire 1 1 cnt8 $end
$var wire 18 C addOut [17:0] $end
$scope module cntr $end
$var wire 1 # clk $end
$var wire 1 0 cntUp $end
$var wire 1 / init0 $end
$var wire 1 $ rst $end
$var reg 3 D cnt [2:0] $end
$upscope $end
$scope module eReg $end
$var wire 1 # clk $end
$var wire 18 E in [17:0] $end
$var wire 1 . init1 $end
$var wire 1 , load $end
$var wire 1 $ rst $end
$var reg 18 F out [17:0] $end
$upscope $end
$scope module lut $end
$var wire 3 G addr [2:0] $end
$var wire 16 H data [15:0] $end
$var reg 16 I dataOut [15:0] $end
$upscope $end
$scope module tReg $end
$var wire 1 # clk $end
$var wire 16 J in [15:0] $end
$var wire 1 - init1 $end
$var wire 1 + load $end
$var wire 1 $ rst $end
$var reg 16 K out [15:0] $end
$upscope $end
$scope module xReg $end
$var wire 1 # clk $end
$var wire 16 L in [15:0] $end
$var wire 1 M init1 $end
$var wire 1 * load $end
$var wire 1 $ rst $end
$var reg 16 N out [15:0] $end
$upscope $end
$upscope $end
$upscope $end
$upscope $end
$enddefinitions $end
$comment Show the parameter values. $end
$dumpall
b1 7
b100 6
b11 5
b0 4
b10 3
b101 2
$end
#0
$dumpvars
bx N
0M
bx L
bx K
bx J
bx I
bx H
bx G
bx F
bx E
bx D
bx C
bx B
bx A
bx @
bx ?
bx >
bx =
bx <
bx ;
bx :
bx 9
b0 8
x1
00
0/
0.
0-
0,
0+
0*
bx )
0(
bx '
bx &
0%
0$
0#
0"
bx !
$end
#5
b0 J
b0 ?
b1111111111111111 >
01
b1111111111111111 @
b1111111111111111 H
b1111111111111111 I
1"
b0 B
b0 D
b0 G
b0 <
b0 N
b0 C
b0 E
b0 =
b0 K
b0 !
b0 )
b0 :
b0 A
b0 F
b0 9
1#
1$
#10
0#
#15
b1 9
1#
b1 8
0"
1%
b0 &
b0 '
b0 ;
b0 L
0$
#20
0#
#25
1/
1.
1-
1*
b10 9
1#
b11 8
0%
#30
0#
#35
b0 >
b0 J
1+
1(
0*
0-
0.
0/
b100 8
b0 ?
b1111111111111111 =
b1111111111111111 K
b11111111111111111 C
b11111111111111111 E
b10000000000000000 !
b10000000000000000 )
b10000000000000000 :
b10000000000000000 A
b10000000000000000 F
b11 9
1#
#40
0#
#45
b1111111111111111 >
1+
0(
b101 8
b100 9
b10000000000000000 C
b10000000000000000 E
b0 =
b0 K
1#
#50
0#
#55
10
1,
0+
b11 8
b101 9
1#
#60
0#
#65
b0 >
1+
1(
0,
00
b100 8
b1000000000000000 @
b1000000000000000 H
b1000000000000000 I
b11 9
b1 B
b1 D
b1 G
1#
#70
0#
#75
b1000000000000000 >
1+
0(
b101 8
b100 9
1#
#80
0#
#85
10
1,
0+
b11 8
b101 9
1#
#90
0#
#95
b0 >
b10101010101011 @
b10101010101011 H
b10101010101011 I
1+
1(
0,
00
b100 8
b10 B
b10 D
b10 G
b11 9
1#
#100
0#
#105
b10101010101011 >
1+
0(
b101 8
b100 9
1#
#110
0#
#115
10
1,
0+
b11 8
b101 9
1#
#120
0#
#125
b0 >
1+
1(
0,
00
b100 8
b101010101011 @
b101010101011 H
b101010101011 I
b11 9
b11 B
b11 D
b11 G
1#
#130
0#
#135
b101010101011 >
1+
0(
b101 8
b100 9
1#
#140
0#
#145
10
1,
0+
b11 8
b101 9
1#
#150
0#
#155
b0 >
b1000100010 @
b1000100010 H
b1000100010 I
1+
1(
0,
00
b100 8
b100 B
b100 D
b100 G
b11 9
1#
#160
0#
#165
b1000100010 >
1+
0(
b101 8
b100 9
1#
#170
0#
#175
10
1,
0+
b11 8
b101 9
1#
#180
0#
#185
b0 >
1+
1(
0,
00
b100 8
b1011011 @
b1011011 H
b1011011 I
b11 9
b101 B
b101 D
b101 G
1#
#190
0#
#195
b1011011 >
1+
0(
b101 8
b100 9
1#
#200
0#
#205
10
1,
0+
b11 8
b101 9
1#
#210
0#
#215
b0 >
b1101 @
b1101 H
b1101 I
1+
1(
0,
00
b100 8
b110 B
b110 D
b110 G
b11 9
1#
#220
0#
#225
b1101 >
1+
0(
b101 8
b100 9
1#
#230
0#
#235
10
1,
0+
b11 8
b101 9
1#
#240
0#
#245
b0 >
11
1+
1(
0,
00
b100 8
b10 @
b10 H
b10 I
b11 9
b111 B
b111 D
b111 G
1#
#250
0#
#255
b10 >
1+
0(
b101 8
b100 9
1#
#260
0#
#265
10
1,
0+
b0 8
b101 9
1#
#270
0#
#275
b1111111111111111 >
01
b1111111111111111 @
b1111111111111111 H
b1111111111111111 I
1"
0,
00
b0 B
b0 D
b0 G
b0 9
1#
#280
0#
#285
1#
#290
0#
#295
1#
#300
0#
#305
1#
#310
0#
#315
1#
#320
0#
#325
1#
#330
b0 C
b0 E
b0 !
b0 )
b0 :
b0 A
b0 F
0#
1$
#335
1#
#340
0#
b1 8
1"
1%
b10000000000000 &
b10000000000000 '
b10000000000000 ;
b10000000000000 L
0$
#345
0"
b1 8
b1 9
1#
#350
0#
b10 8
0%
#355
1/
1.
1-
1*
b11 8
b10 9
1#
#360
0#
#365
b10000000000000 >
b1111111111111 J
1+
1(
0*
0-
0.
0/
b100 8
b10000000000000 <
b10000000000000 N
b11111111111111110000000000000 ?
b1111111111111111 =
b1111111111111111 K
b11111111111111111 C
b11111111111111111 E
b10000000000000000 !
b10000000000000000 )
b10000000000000000 :
b10000000000000000 A
b10000000000000000 F
b11 9
1#
#370
0#
#375
b1111111111111111 >
1+
0(
b101 8
b1111111111110 J
b100 9
b11111111111101110000000000001 ?
b10001111111111111 C
b10001111111111111 E
b1111111111111 =
b1111111111111 K
1#
#380
0#
#385
b1111111111101 J
10
1,
0+
b11 8
b11111111111011110000000000010 ?
b10001111111111110 C
b10001111111111110 E
b1111111111110 =
b1111111111110 K
b101 9
1#
#390
0#
#395
b1111111111 J
b11111111111100000000000000 ?
b10000000000000 >
1+
1(
0,
00
b100 8
b1000000000000000 @
b1000000000000000 H
b1000000000000000 I
b11 9
b10011111111111100 C
b10011111111111100 E
b10001111111111110 !
b10001111111111110 )
b10001111111111110 :
b10001111111111110 A
b10001111111111110 F
b1 B
b1 D
b1 G
1#
#400
0#
#405
b1000000000000000 >
b111111111 J
1+
0(
b101 8
b1111111111000000000000000 ?
b10010001111111101 C
b10010001111111101 E
b1111111111 =
b1111111111 K
b100 9
1#
#410
0#
#415
10
1,
0+
b11 8
b11111111 J
b101 9
b111111111000000000000000 ?
b10010000111111101 C
b10010000111111101 E
b111111111 =
b111111111 K
1#
#420
0#
#425
b111111 J
b1111111110000000000000 ?
b10000000000000 >
b10101010101011 @
b10101010101011 H
b10101010101011 I
1+
1(
0,
00
b100 8
b10 B
b10 D
b10 G
b10010001111111100 C
b10010001111111100 E
b10010000111111101 !
b10010000111111101 )
b10010000111111101 :
b10010000111111101 A
b10010000111111101 F
b11 9
1#
#430
0#
#435
b10101010101011 >
1+
0(
b101 8
b1010 J
b100 9
b10101000000000010101 ?
b10010001000111100 C
b10010001000111100 E
b111111 =
b111111 K
1#
#440
0#
#445
b1 J
10
1,
0+
b11 8
b11010101010101110 ?
b10010001000000111 C
b10010001000000111 E
b1010 =
b1010 K
b101 9
1#
#450
0#
#455
b10100000000000000 ?
b10000000000000 >
1+
1(
0,
00
b100 8
b101010101011 @
b101010101011 H
b101010101011 I
b11 9
b10010001000010001 C
b10010001000010001 E
b10010001000000111 !
b10010001000000111 )
b10010001000000111 :
b10010001000000111 A
b10010001000000111 F
b11 B
b11 D
b11 G
1#
#460
0#
#465
b101010101011 >
b0 J
1+
0(
b101 8
b101010101011 ?
b10010001000001000 C
b10010001000001000 E
b1 =
b1 K
b100 9
1#
#470
0#
#475
10
1,
0+
b11 8
b101 9
b0 ?
b10010001000000111 C
b10010001000000111 E
b0 =
b0 K
1#
#480
0#
#485
b10000000000000 >
b1000100010 @
b1000100010 H
b1000100010 I
1+
1(
0,
00
b100 8
b100 B
b100 D
b100 G
b11 9
1#
#490
0#
#495
b1000100010 >
1+
0(
b101 8
b100 9
1#
#500
0#
#505
10
1,
0+
b11 8
b101 9
1#
#510
0#
#515
b10000000000000 >
1+
1(
0,
00
b100 8
b1011011 @
b1011011 H
b1011011 I
b11 9
b101 B
b101 D
b101 G
1#
#520
0#
#525
b1011011 >
1+
0(
b101 8
b100 9
1#
#530
0#
#535
10
1,
0+
b11 8
b101 9
1#
#540
0#
#545
b10000000000000 >
b1101 @
b1101 H
b1101 I
1+
1(
0,
00
b100 8
b110 B
b110 D
b110 G
b11 9
1#
#550
0#
#555
b1101 >
1+
0(
b101 8
b100 9
1#
#560
0#
#565
10
1,
0+
b11 8
b101 9
1#
#570
0#
#575
b10000000000000 >
11
1+
1(
0,
00
b100 8
b10 @
b10 H
b10 I
b11 9
b111 B
b111 D
b111 G
1#
#580
0#
#585
b10 >
1+
0(
b101 8
b100 9
1#
#590
0#
#595
10
1,
0+
b0 8
b101 9
1#
#600
0#
#605
b1111111111111111 >
01
b1111111111111111 @
b1111111111111111 H
b1111111111111111 I
1"
0,
00
b0 B
b0 D
b0 G
b0 9
1#
#610
0#
#615
1#
#620
0#
#625
1#
#630
0#
#635
1#
#640
0#
#645
1#
#650
0#
#655
b0 C
b0 E
b0 !
b0 )
b0 :
b0 A
b0 F
b0 <
b0 N
1#
1$
#660
0#
#665
b1 9
1#
b1 8
0"
1%
b100000000000000 &
b100000000000000 '
b100000000000000 ;
b100000000000000 L
0$
#670
0#
#675
1/
1.
1-
1*
b10 9
1#
b11 8
0%
#680
0#
#685
b100000000000000 >
1+
1(
0*
0-
0.
0/
b100 8
b11111111111111 J
b11 9
b10000000000000000 !
b10000000000000000 )
b10000000000000000 :
b10000000000000000 A
b10000000000000000 F
b111111111111111100000000000000 ?
b11111111111111111 C
b11111111111111111 E
b1111111111111111 =
b1111111111111111 K
b100000000000000 <
b100000000000000 N
1#
#690
0#
#695
b1111111111111111 >
b11111111111110 J
1+
0(
b101 8
b111111111111101100000000000001 ?
b10011111111111111 C
b10011111111111111 E
b11111111111111 =
b11111111111111 K
b100 9
1#
#700
0#
#705
10
1,
0+
b11 8
b11111111111101 J
b101 9
b111111111111011100000000000010 ?
b10011111111111110 C
b10011111111111110 E
b11111111111110 =
b11111111111110 K
1#
#710
0#
#715
b111111111111 J
b1111111111111000000000000000 ?
b100000000000000 >
b1000000000000000 @
b1000000000000000 H
b1000000000000000 I
1+
1(
0,
00
b100 8
b1 B
b1 D
b1 G
b10111111111111100 C
b10111111111111100 E
b10011111111111110 !
b10011111111111110 )
b10011111111111110 :
b10011111111111110 A
b10011111111111110 F
b11 9
1#
#720
0#
#725
b1000000000000000 >
1+
0(
b101 8
b11111111111 J
b100 9
b111111111111000000000000000 ?
b10100111111111101 C
b10100111111111101 E
b111111111111 =
b111111111111 K
1#
#730
0#
#735
b1111111111 J
10
1,
0+
b11 8
b11111111111000000000000000 ?
b10100011111111101 C
b10100011111111101 E
b11111111111 =
b11111111111 K
b101 9
1#
#740
0#
#745
b111111111 J
b1111111111100000000000000 ?
b100000000000000 >
1+
1(
0,
00
b100 8
b10101010101011 @
b10101010101011 H
b10101010101011 I
b11 9
b10100111111111100 C
b10100111111111100 E
b10100011111111101 !
b10100011111111101 )
b10100011111111101 :
b10100011111111101 A
b10100011111111101 F
b10 B
b10 D
b10 G
1#
#750
0#
#755
b10101010101011 >
b1010101 J
1+
0(
b101 8
b10101010010101101010101 ?
b10100100111111100 C
b10100100111111100 E
b111111111 =
b111111111 K
b100 9
1#
#760
0#
#765
10
1,
0+
b11 8
b1110 J
b101 9
b11100010101011000111 ?
b10100100001010010 C
b10100100001010010 E
b1010101 =
b1010101 K
1#
#770
0#
#775
b10101 J
b101010100000000000000 ?
b100000000000000 >
b101010101011 @
b101010101011 H
b101010101011 I
1+
1(
0,
00
b100 8
b11 B
b11 D
b11 G
b10100100010100111 C
b10100100010100111 E
b10100100001010010 !
b10100100001010010 )
b10100100001010010 :
b10100100001010010 A
b10100100001010010 F
b11 9
1#
#780
0#
#785
b101010101011 >
1+
0(
b101 8
b0 J
b100 9
b1110000000000111 ?
b10100100001100111 C
b10100100001100111 E
b10101 =
b10101 K
1#
#790
0#
#795
10
1,
0+
b11 8
b0 ?
b10100100001010010 C
b10100100001010010 E
b0 =
b0 K
b101 9
1#
#800
0#
#805
b100000000000000 >
1+
1(
0,
00
b100 8
b1000100010 @
b1000100010 H
b1000100010 I
b11 9
b100 B
b100 D
b100 G
1#
#810
0#
#815
b1000100010 >
1+
0(
b101 8
b100 9
1#
#820
0#
#825
10
1,
0+
b11 8
b101 9
1#
#830
0#
#835
b100000000000000 >
b1011011 @
b1011011 H
b1011011 I
1+
1(
0,
00
b100 8
b101 B
b101 D
b101 G
b11 9
1#
#840
0#
#845
b1011011 >
1+
0(
b101 8
b100 9
1#
#850
0#
#855
10
1,
0+
b11 8
b101 9
1#
#860
0#
#865
b100000000000000 >
1+
1(
0,
00
b100 8
b1101 @
b1101 H
b1101 I
b11 9
b110 B
b110 D
b110 G
1#
#870
0#
#875
b1101 >
1+
0(
b101 8
b100 9
1#
#880
0#
#885
10
1,
0+
b11 8
b101 9
1#
#890
0#
#895
11
b100000000000000 >
b10 @
b10 H
b10 I
1+
1(
0,
00
b100 8
b111 B
b111 D
b111 G
b11 9
1#
#900
0#
#905
b10 >
1+
0(
b101 8
b100 9
1#
#910
0#
#915
10
1,
0+
b0 8
b101 9
1#
#920
0#
#925
b1111111111111111 >
01
1"
0,
00
b1111111111111111 @
b1111111111111111 H
b1111111111111111 I
b0 9
b0 B
b0 D
b0 G
1#
#930
0#
#935
1#
#940
0#
#945
1#
#950
0#
#955
1#
#960
0#
#965
1#
#970
0#
#975
1#
#980
b0 C
b0 E
b0 !
b0 )
b0 :
b0 A
b0 F
b0 <
b0 N
0#
1$
#985
1#
#990
0#
b1 8
1"
1%
b1000000000000000 &
b1000000000000000 '
b1000000000000000 ;
b1000000000000000 L
0$
#995
0"
b1 8
b1 9
1#
#1000
0#
b10 8
0%
#1005
1/
1.
1-
1*
b11 8
b10 9
1#
#1010
0#
#1015
b1000000000000000 >
1+
1(
0*
0-
0.
0/
b100 8
b111111111111111 J
b11 9
b10000000000000000 !
b10000000000000000 )
b10000000000000000 :
b10000000000000000 A
b10000000000000000 F
b1111111111111111000000000000000 ?
b11111111111111111 C
b11111111111111111 E
b1111111111111111 =
b1111111111111111 K
b1000000000000000 <
b1000000000000000 N
1#
#1020
0#
#1025
b1111111111111111 >
b111111111111110 J
1+
0(
b101 8
b1111111111111101000000000000001 ?
b10111111111111111 C
b10111111111111111 E
b111111111111111 =
b111111111111111 K
b100 9
1#
#1030
0#
#1035
10
1,
0+
b11 8
b111111111111101 J
b101 9
b1111111111111011000000000000010 ?
b10111111111111110 C
b10111111111111110 E
b111111111111110 =
b111111111111110 K
1#
#1040
0#
#1045
b11111111111111 J
b111111111111110000000000000000 ?
b1000000000000000 >
b1000000000000000 @
b1000000000000000 H
b1000000000000000 I
1+
1(
0,
00
b100 8
b1 B
b1 D
b1 G
b11111111111111100 C
b11111111111111100 E
b10111111111111110 !
b10111111111111110 )
b10111111111111110 :
b10111111111111110 A
b10111111111111110 F
b11 9
1#
#1050
0#
#1055
1+
0(
b101 8
b1111111111111 J
b100 9
b11111111111111000000000000000 ?
b11011111111111101 C
b11011111111111101 E
b11111111111111 =
b11111111111111 K
1#
#1060
0#
#1065
b111111111111 J
10
1,
0+
b11 8
b1111111111111000000000000000 ?
b11001111111111101 C
b11001111111111101 E
b1111111111111 =
b1111111111111 K
b101 9
1#
#1070
0#
#1075
1+
1(
0,
00
b100 8
b10101010101011 @
b10101010101011 H
b10101010101011 I
b11 9
b11011111111111100 C
b11011111111111100 E
b11001111111111101 !
b11001111111111101 )
b11001111111111101 :
b11001111111111101 A
b11001111111111101 F
b10 B
b10 D
b10 G
1#
#1080
0#
#1085
b10101010101011 >
b1010101010 J
1+
0(
b101 8
b10101010101000010101010101 ?
b11010111111111100 C
b11010111111111100 E
b111111111111 =
b111111111111 K
b100 9
1#
#1090
0#
#1095
10
1,
0+
b11 8
b1110001 J
b101 9
b11100011010101110001110 ?
b11010001010100111 C
b11010001010100111 E
b1010101010 =
b1010101010 K
1#
#1100
0#
#1105
b101010101 J
b1010101010000000000000000 ?
b1000000000000000 >
b101010101011 @
b101010101011 H
b101010101011 I
1+
1(
0,
00
b100 8
b11 B
b11 D
b11 G
b11010010101010001 C
b11010010101010001 E
b11010001010100111 !
b11010001010100111 )
b11010001010100111 :
b11010001010100111 A
b11010001010100111 F
b11 9
1#
#1110
0#
#1115
b101010101011 >
1+
0(
b101 8
b1110 J
b100 9
b11100011010111000111 ?
b11010001111111100 C
b11010001111111100 E
b101010101 =
b101010101 K
1#
#1120
0#
#1125
b0 J
10
1,
0+
b11 8
b1001010101011010 ?
b11010001010110101 C
b11010001010110101 E
b1110 =
b1110 K
b101 9
1#
#1130
0#
#1135
b111 J
b1110000000000000000 ?
b1000000000000000 >
1+
1(
0,
00
b100 8
b1000100010 @
b1000100010 H
b1000100010 I
b11 9
b11010001011000011 C
b11010001011000011 E
b11010001010110101 !
b11010001010110101 )
b11010001010110101 :
b11010001010110101 A
b11010001010110101 F
b100 B
b100 D
b100 G
1#
#1140
0#
#1145
b1000100010 >
b0 J
1+
0(
b101 8
b111011101110 ?
b11010001010111100 C
b11010001010111100 E
b111 =
b111 K
b100 9
1#
#1150
0#
#1155
10
1,
0+
b11 8
b101 9
b0 ?
b11010001010110101 C
b11010001010110101 E
b0 =
b0 K
1#
#1160
0#
#1165
b1000000000000000 >
b1011011 @
b1011011 H
b1011011 I
1+
1(
0,
00
b100 8
b101 B
b101 D
b101 G
b11 9
1#
#1170
0#
#1175
b1011011 >
1+
0(
b101 8
b100 9
1#
#1180
0#
#1185
10
1,
0+
b11 8
b101 9
1#
#1190
0#
#1195
b1000000000000000 >
1+
1(
0,
00
b100 8
b1101 @
b1101 H
b1101 I
b11 9
b110 B
b110 D
b110 G
1#
#1200
0#
#1205
b1101 >
1+
0(
b101 8
b100 9
1#
#1210
0#
#1215
10
1,
0+
b11 8
b101 9
1#
#1220
0#
#1225
11
b1000000000000000 >
b10 @
b10 H
b10 I
1+
1(
0,
00
b100 8
b111 B
b111 D
b111 G
b11 9
1#
#1230
0#
#1235
b10 >
1+
0(
b101 8
b100 9
1#
#1240
0#
#1245
10
1,
0+
b0 8
b101 9
1#
#1250
0#
#1255
b1111111111111111 >
01
1"
0,
00
b1111111111111111 @
b1111111111111111 H
b1111111111111111 I
b0 9
b0 B
b0 D
b0 G
1#
#1260
0#
#1265
1#
#1270
0#
#1275
1#
#1280
0#
#1285
1#
#1290
0#
#1295
1#
#1300
0#
#1305
b0 <
b0 N
b0 C
b0 E
b0 !
b0 )
b0 :
b0 A
b0 F
1#
1$
#1310
0#
#1315
b1 9
1#
b1 8
0"
1%
b1111111111111111 &
b1111111111111111 '
b1111111111111111 ;
b1111111111111111 L
0$
#1320
0#
#1325
1/
1.
1-
1*
b10 9
1#
b11 8
0%
#1330
0#
#1335
b1111111111111110 J
1+
1(
0*
0-
0.
0/
b100 8
b1111111111111111 <
b1111111111111111 N
b11111111111111100000000000000001 ?
b1111111111111111 =
b1111111111111111 K
b11111111111111111 C
b11111111111111111 E
b10000000000000000 !
b10000000000000000 )
b10000000000000000 :
b10000000000000000 A
b10000000000000000 F
b11 9
1#
#1340
0#
#1345
1+
0(
b101 8
b1111111111111101 J
b100 9
b11111111111111010000000000000010 ?
b11111111111111110 C
b11111111111111110 E
b1111111111111110 =
b1111111111111110 K
1#
#1350
0#
#1355
b1111111111111100 J
10
1,
0+
b11 8
b11111111111111000000000000000011 ?
b11111111111111101 C
b11111111111111101 E
b1111111111111101 =
b1111111111111101 K
b101 9
1#
#1360
0#
#1365
1+
1(
0,
00
b100 8
b1000000000000000 @
b1000000000000000 H
b1000000000000000 I
b11 9
b101111111111111010 C
b101111111111111010 E
b11111111111111101 !
b11111111111111101 )
b11111111111111101 :
b11111111111111101 A
b11111111111111101 F
b1 B
b1 D
b1 G
1#
#1370
0#
#1375
b1000000000000000 >
b111111111111110 J
1+
0(
b101 8
b1111111111111100000000000000000 ?
b101111111111111001 C
b101111111111111001 E
b1111111111111100 =
b1111111111111100 K
b100 9
1#
#1380
0#
#1385
10
1,
0+
b11 8
b11111111111111 J
b101 9
b111111111111110000000000000000 ?
b100111111111111011 C
b100111111111111011 E
b111111111111110 =
b111111111111110 K
1#
#1390
0#
#1395
b111111111111101 J
b1111111111111011000000000000010 ?
b1111111111111111 >
b10101010101011 @
b10101010101011 H
b10101010101011 I
1+
1(
0,
00
b100 8
b10 B
b10 D
b10 G
b101111111111111001 C
b101111111111111001 E
b100111111111111011 !
b100111111111111011 )
b100111111111111011 :
b100111111111111011 A
b100111111111111011 F
b11 9
1#
#1400
0#
#1405
b10101010101011 >
1+
0(
b101 8
b1010101010100 J
b100 9
b10101010101001111111111111111 ?
b101111111111111000 C
b101111111111111000 E
b111111111111101 =
b111111111111101 K
1#
#1410
0#
