lnCU.v
// controller unit module for ln (state machine)
module lnCU (input clk, rst, start, cnt8,
  output reg done, ldX, initT1, initLN1, ldT, ldLN, init0, cntUp, selXR);

  // states
  reg [2:0] pstate, nstate;
  parameter IDLE = 0, STARTING = 1, GETINPUT = 2, GETINPUT2 = 3, MULT1 = 4, MULT2 = 5, ADD = 6;

  // registers
  always @(posedge clk, posedge rst) begin
    if (rst == 1)
      pstate <= IDLE;
    else
      pstate <= nstate;
  end

  // combinational part
  always @(pstate, start, cnt8) begin
    nstate = IDLE; // default
    done = 0;
    {ldX, initT1, initLN1, ldT, ldLN, init0, cntUp, selXR} = 8'b0;
    // 1. State: IDLE
    if (pstate == IDLE) begin nstate = (start == 1) ? STARTING : IDLE;
      done = 1;
    end
    // 2. State: STARTING
    if (pstate == STARTING) begin 
      nstate = (start == 0) ? GETINPUT: STARTING;
    end
    // 3. State: GETINPUT
    if (pstate == GETINPUT) begin 
      nstate = GETINPUT2;
      ldX = 1; // new extra state for delay
    end
    // 4. State: GETINPUT2
    if (pstate == GETINPUT2) begin 
      nstate = MULT1;
      initT1 = 1; initLN1 = 1; init0 = 1; // ln = xin, term = 1
    end
    // 5. State: MULT1
    if (pstate == MULT1) begin 
      nstate = MULT2;
      selXR = 1; ldT = 1;
    end
    // 6. State: MULT2
    if (pstate == MULT2) begin 
      nstate = ADD;
      ldT = 1;
    end
    // 7. State: ADD 
    if (pstate == ADD) begin 
      nstate = (cnt8 == 1)? IDLE : MULT1;
      ldLN = 1; cntUp = 1;
    end
  end

endmodule

sinReg18.v
// 18 bit registers for sin
module sinReg18 (input clk, rst, init1, load, input [17:0] initS, input [17:0] in, output reg [17:0] out);
  always @ (posedge clk, posedge rst) begin
    if (rst == 1)
      out <= 0;
    else begin
      if (init1 == 1)
        out <= initS;
      else begin
        if (load == 1)
          out <= in;
      end
    end
  end
endmodule

reg16.v
// 16 bit registers for input busses
module reg16 (input clk, rst, init1, load, input [15:0] in, output reg [15:0] out);
  always @ (posedge clk, posedge rst) begin
    if (rst == 1)
      out <= 0;
    else begin
      if (init1 == 1)
        out <= 16'hFFFF;
      else begin
        if (load == 1)
          out <= in;
      end
    end
  end
endmodule

lnLUT.v
// look up table module for ln(x+1)
module lnLUT (input [2:0]addr, output [15:0] data);
  reg [15:0] dataOut;
  always @(addr) begin
    case(addr)
      0: dataOut = 16'h8000; // 1/2
      1: dataOut = 16'h5555; // 1/3
      2: dataOut = 16'h4000; // 1/4
      3: dataOut = 16'h3333; // 1/5
      4: dataOut = 16'h2AAA; // 1/6
      5: dataOut = 16'h2492; // 1/7
      6: dataOut = 16'h2000; // 1/8
      7: dataOut = 16'h0000; // 1/9
    endcase
  end
  assign data = dataOut;
endmodule

cntReg.v
// 3-bit counter module
module cntReg (input clk, rst, cntUp, init0, output reg [2:0] cnt);
  always @ (posedge clk, posedge rst) begin
    if (rst == 1)
      cnt <= 0;
    else begin
      if (init0 == 1)
        cnt <= 0;
      else begin
        if (cntUp == 1)
          cnt <= cnt + 1;
      end
    end
  end
endmodule

lnDU.v
// datapath module for ln(x + 1)
module lnDU (input clk, rst, cntUp, init0, ldX, ldT, initT1, ldLN, initLN1, selXR,
  input [15:0] xBus, output cnt8, output [17:0] rBus);

  // mid-level signals
  wire [2:0] cntOut;
  wire [17:0] lnOut, addOut;
  wire [15:0] lutOut, xOut, tOut, muxOut;
  wire [31:0] mulOut;
  wire isOdd;
  wire [31:0] xSquared;

  // module instantiations 
  cntReg cntr(clk, rst, cntUp, init0, cntOut);
  lnLUT lut(cntOut, lutOut);
  reg16 xReg(clk, rst, 1'b0, ldX, xBus, xOut); // no need to initialize
  reg16 tReg(clk, rst, initT1, ldT, mulOut[31:16], tOut); // t = 1 in the begining
  sinReg18 lnReg(clk, rst, initLN1, ldLN, {2'b00, xOut}, addOut, lnOut); // ln = xin in init 

  // add sub assignment: if it's odd cntOut[0] would be 1
  assign isOdd = cntOut[0]; // new

  // output assigning
  assign muxOut = (selXR == 1) ? xOut : lutOut; // mux
  assign mulOut = (muxOut * tOut); 
  assign addOut = (isOdd == 1) ? lnOut - {2'b00, tOut} : lnOut + {2'b00, tOut}; // new

  // final output
  assign rBus = lnOut;
  assign cnt8 = (cntOut == 3'b111) ? 1 : 0;

endmodule

lnTOP.v
// top module for ln
module lnTop (input clk, rst, start, input [15:0] xBus, output [17:0] rBus, output done);
  // 1-bit wires 
  wire cntUp, init0, ldX, ldT, initT1, initLN1, selXR, cnt8;

  // datapath
  lnDU du(clk, rst, cntUp, init0, ldX, ldT, initT1, ldLN, initLN1, selXR, xBus, cnt8, rBus);

  // controller
  lnCU cp(clk, rst, start, cnt8, done, ldX, initT1, initLN1, ldT, ldLN, init0, cntUp, selXR);

endmodule

lnTB.v
// test bech for ln module
`timescale 1ns/1ns

module lnTB ();
  reg clk = 0;
  reg rst = 0;
  reg start = 0;
  reg [15:0] xBus;
  wire done;
  wire [17:0] rBus;

  lnTop ln(clk, rst, start, xBus, rBus, done);

  // generating clock behaviour
  always #5 clk <= ~clk;
  initial begin
    // Dump waveform data to a file.
    $dumpfile("ln_sim.vcd");
    $dumpvars(0, lnTB);

    // x = 0 => ln(x + 1) = ln(1.0) = 0.0 
    #5;
    rst = 1;

    #5;
    #5;
    rst = 0;
    xBus = 0;
    start = 1;

    #5;
    #5;
    start = 0;

    #300;

    // x = 0.125 => ln(x + 1) = ln(1.125) = 0.117783
    #5;
    rst = 1;

    #5;
    #5;
    rst = 0;
    xBus = 16'h2000; // 0.125
    start = 1;

    #5;
    #5;
    start = 0;

    #300;

    // x = 0.25 => ln(x + 1) = ln(1.25) = 0.223143
    #5;
    rst = 1;

    #5;
    #5;
    rst = 0;
    xBus = 16'h4000; // 0.25
    start = 1;

    #5;
    #5;
    start = 0;

    #300;
    // x = 0.5 => ln(x + 1) = ln(1.5) = 0.405465
    #5;
    rst = 1;

    #5;
    #5;
    rst = 0;
    xBus = 16'h8000; // 0.5
    start = 1;

    #5;
    #5;
    start = 0;

    #300;
    // x = 1 => ln(x + 1) = ln(2) = 0.69314
    #5;
    rst = 1;

    #5;
    #5;
    rst = 0;
    xBus = 16'hFFFF; // 1 
    start = 1;

    #5;
    #5;
    start = 0;

    #300;

    // x = 1.5 => ln(2.5) ≈ 0.91629
    #5; rst = 1;
    #5; #5; rst = 0; xBus = 16'h18000; start = 1;
    #5; #5; start = 0;
    #300;

    // x = 2 => ln(3) ≈ 1.0986
    #5; rst = 1;
    #5; #5; rst = 0; xBus = 16'h20000; start = 1;
    #5; #5; start = 0;
    #300;

    // x = 2.5 => ln(3.5) ≈ 1.2528
    #5; rst = 1;
    #5; #5; rst = 0; xBus = 16'h28000; start = 1;
    #5; #5; start = 0;
    #300;

    // x = 3 => ln(4) ≈ 1.3863
    #5; rst = 1;
    #5; #5; rst = 0; xBus = 16'h30000; start = 1;
    #5; #5; start = 0;
    #300;

    // x = 3.5 => ln(4.5) ≈ 1.5041
    #5; rst = 1;
    #5; #5; rst = 0; xBus = 16'h38000; start = 1;
    #5; #5; start = 0;
    #300;


    $finish; 
  end

endmodule

ln_sim.vcd
$date
	Fri Feb  7 14:49:37 2025
$end
$version
	Icarus Verilog
$end
$timescale
	1ns
$end
$scope module lnTB $end
$var wire 18 ! rBus [17:0] $end
$var wire 1 " done $end
$var reg 1 # clk $end
$var reg 1 $ rst $end
$var reg 1 % start $end
$var reg 16 & xBus [15:0] $end
$scope module ln $end
$var wire 1 # clk $end
$var wire 1 $ rst $end
$var wire 1 % start $end
$var wire 16 ' xBus [15:0] $end
$var wire 1 ( selXR $end
$var wire 18 ) rBus [17:0] $end
$var wire 1 * ldX $end
$var wire 1 + ldT $end
$var wire 1 , ldLN $end
$var wire 1 - initT1 $end
$var wire 1 . initLN1 $end
$var wire 1 / init0 $end
$var wire 1 " done $end
$var wire 1 0 cntUp $end
$var wire 1 1 cnt8 $end
$scope module cp $end
$var wire 1 # clk $end
$var wire 1 $ rst $end
$var wire 1 % start $end
$var wire 1 1 cnt8 $end
$var parameter 32 2 ADD $end
$var parameter 32 3 GETINPUT $end
$var parameter 32 4 GETINPUT2 $end
$var parameter 32 5 IDLE $end
$var parameter 32 6 MULT1 $end
$var parameter 32 7 MULT2 $end
$var parameter 32 8 STARTING $end
$var reg 1 0 cntUp $end
$var reg 1 " done $end
$var reg 1 / init0 $end
$var reg 1 . initLN1 $end
$var reg 1 - initT1 $end
$var reg 1 , ldLN $end
$var reg 1 + ldT $end
$var reg 1 * ldX $end
$var reg 3 9 nstate [2:0] $end
$var reg 3 : pstate [2:0] $end
$var reg 1 ( selXR $end
$upscope $end
$scope module du $end
$var wire 1 # clk $end
$var wire 1 0 cntUp $end
$var wire 1 / init0 $end
$var wire 1 . initLN1 $end
$var wire 1 - initT1 $end
$var wire 1 , ldLN $end
$var wire 1 + ldT $end
$var wire 1 * ldX $end
$var wire 18 ; rBus [17:0] $end
$var wire 1 $ rst $end
$var wire 1 ( selXR $end
$var wire 16 < xBus [15:0] $end
$var wire 16 = xOut [15:0] $end
$var wire 16 > tOut [15:0] $end
$var wire 16 ? muxOut [15:0] $end
$var wire 32 @ mulOut [31:0] $end
$var wire 16 A lutOut [15:0] $end
$var wire 18 B lnOut [17:0] $end
$var wire 1 C isOdd $end
$var wire 3 D cntOut [2:0] $end
$var wire 1 1 cnt8 $end
$var wire 18 E addOut [17:0] $end
$scope module cntr $end
$var wire 1 # clk $end
$var wire 1 0 cntUp $end
$var wire 1 / init0 $end
$var wire 1 $ rst $end
$var reg 3 F cnt [2:0] $end
$upscope $end
$scope module lnReg $end
$var wire 1 # clk $end
$var wire 18 G in [17:0] $end
$var wire 1 . init1 $end
$var wire 18 H initS [17:0] $end
$var wire 1 , load $end
$var wire 1 $ rst $end
$var reg 18 I out [17:0] $end
$upscope $end
$scope module lut $end
$var wire 3 J addr [2:0] $end
$var wire 16 K data [15:0] $end
$var reg 16 L dataOut [15:0] $end
$upscope $end
$scope module tReg $end
$var wire 1 # clk $end
$var wire 16 M in [15:0] $end
$var wire 1 - init1 $end
$var wire 1 + load $end
$var wire 1 $ rst $end
$var reg 16 N out [15:0] $end
$upscope $end
$scope module xReg $end
$var wire 1 # clk $end
$var wire 16 O in [15:0] $end
$var wire 1 P init1 $end
$var wire 1 * load $end
$var wire 1 $ rst $end
$var reg 16 Q out [15:0] $end
$upscope $end
$upscope $end
$upscope $end
$upscope $end
$enddefinitions $end
$comment Show the parameter values. $end
$dumpall
b1 8
b101 7
b100 6
b0 5
b11 4
b10 3
b110 2
$end
#0
$dumpvars
bx Q
0P
bx O
bx N
bx M
bx L
bx K
bx J
bx I
b0xxxxxxxxxxxxxxxx H
bx G
bx F
bx E
bx D
xC
bx B
bx A
bx @
bx ?
bx >
bx =
bx <
bx ;
bx :
b0 9
x1
00
0/
0.
0-
0,
0+
0*
bx )
0(
bx '
bx &
0%
0$
0#
0"
bx !
$end
#5
b0 M
b0 @
b1000000000000000 ?
01
b1000000000000000 A
b1000000000000000 K
b1000000000000000 L
0C
b0 E
b0 G
1"
b0 D
b0 F
b0 J
b0 H
b0 =
b0 Q
b0 >
b0 N
b0 !
b0 )
b0 ;
b0 B
b0 I
b0 :
1#
1$
#10
0#
#15
b1 :
1#
b1 9
0"
1%
b0 &
b0 '
b0 <
b0 O
0$
#20
0#
#25
1*
b10 :
1#
b11 9
0%
#30
0#
#35
1/
1.
1-
0*
b100 9
b11 :
1#
#40
0#
#45
b0 ?
1+
1(
0-
0.
0/
b101 9
b1111111111111111 E
b1111111111111111 G
b0 M
b100 :
b0 @
b1111111111111111 >
b1111111111111111 N
1#
#50
0#
#55
b1000000000000000 ?
b0 E
b0 G
1+
0(
b110 9
b0 >
b0 N
b101 :
1#
#60
0#
#65
10
1,
0+
b100 9
b110 :
1#
#70
0#
#75
b0 ?
b101010101010101 A
b101010101010101 K
b101010101010101 L
1C
1+
1(
0,
00
b101 9
b1 D
b1 F
b1 J
b100 :
1#
#80
0#
#85
b101010101010101 ?
1+
0(
b110 9
b101 :
1#
#90
0#
#95
10
1,
0+
b100 9
b110 :
1#
#100
0#
#105
b0 ?
1+
1(
0,
00
b101 9
b100000000000000 A
b100000000000000 K
b100000000000000 L
0C
b100 :
b10 D
b10 F
b10 J
1#
#110
0#
#115
b100000000000000 ?
1+
0(
b110 9
b101 :
1#
#120
0#
#125
10
1,
0+
b100 9
b110 :
1#
#130
0#
#135
b0 ?
b11001100110011 A
b11001100110011 K
b11001100110011 L
1C
1+
1(
0,
00
b101 9
b11 D
b11 F
b11 J
b100 :
1#
#140
0#
#145
b11001100110011 ?
1+
0(
b110 9
b101 :
1#
#150
0#
#155
10
1,
0+
b100 9
b110 :
1#
#160
0#
#165
b0 ?
1+
1(
0,
00
b101 9
b10101010101010 A
b10101010101010 K
b10101010101010 L
0C
b100 :
b100 D
b100 F
b100 J
1#
#170
0#
#175
b10101010101010 ?
1+
0(
b110 9
b101 :
1#
#180
0#
#185
10
1,
0+
b100 9
b110 :
1#
#190
0#
#195
b0 ?
b10010010010010 A
b10010010010010 K
b10010010010010 L
1C
1+
1(
0,
00
b101 9
b101 D
b101 F
b101 J
b100 :
1#
#200
0#
#205
b10010010010010 ?
1+
0(
b110 9
b101 :
1#
#210
0#
#215
10
1,
0+
b100 9
b110 :
1#
#220
0#
#225
b0 ?
1+
1(
0,
00
b101 9
b10000000000000 A
b10000000000000 K
b10000000000000 L
0C
b100 :
b110 D
b110 F
b110 J
1#
#230
0#
#235
b10000000000000 ?
1+
0(
b110 9
b101 :
1#
#240
0#
#245
10
1,
0+
b100 9
b110 :
1#
#250
0#
#255
11
b0 ?
b0 A
b0 K
b0 L
1C
1+
1(
0,
00
b101 9
b111 D
b111 F
b111 J
b100 :
1#
#260
0#
#265
1+
0(
b110 9
b101 :
1#
#270
0#
#275
10
1,
0+
b0 9
b110 :
1#
#280
0#
#285
b1000000000000000 ?
01
1"
0,
00
b1000000000000000 A
b1000000000000000 K
b1000000000000000 L
0C
b0 :
b0 D
b0 F
b0 J
1#
#290
0#
#295
1#
#300
0#
#305
1#
#310
0#
#315
1#
#320
0#
#325
1#
#330
0#
1$
#335
1#
#340
0#
b1 9
1"
1%
b10000000000000 &
b10000000000000 '
b10000000000000 <
b10000000000000 O
0$
#345
0"
b1 9
b1 :
1#
#350
0#
b10 9
0%
#355
1*
b11 9
b10 :
1#
#360
0#
#365
1/
1.
1-
0*
b100 9
b10000000000000 H
b10000000000000 =
b10000000000000 Q
b11 :
1#
#370
0#
#375
b10000000000000 ?
1+
1(
0-
0.
0/
b101 9
b10001111111111111 E
b10001111111111111 G
b1111111111111 M
b100 :
b10000000000000 !
b10000000000000 )
b10000000000000 ;
b10000000000000 B
b10000000000000 I
b11111111111111110000000000000 @
b1111111111111111 >
b1111111111111111 N
1#
#380
0#
#385
b1000000000000000 ?
b11111111111111 E
b11111111111111 G
b111111111111 M
1+
0(
b110 9
b1111111111111000000000000000 @
b1111111111111 >
b1111111111111 N
b101 :
1#
#390
0#
#395
10
1,
0+
b100 9
b10111111111111 E
b10111111111111 G
b11111111111 M
b110 :
b111111111111000000000000000 @
b111111111111 >
b111111111111 N
1#
#400
0#
#405
b111111111 M
b1111111111110000000000000 @
b10000000000000 ?
b101010101010101 A
b101010101010101 K
b101010101010101 L
1C
b10000000000000 E
b10000000000000 G
1+
1(
0,
00
b101 9
b1 D
b1 F
b1 J
b10111111111111 !
b10111111111111 )
b10111111111111 ;
b10111111111111 B
b10111111111111 I
b100 :
1#
#410
0#
#415
b101010101010101 ?
1+
0(
b110 9
b10111000000000 E
b10111000000000 G
b10101010 M
b101 :
b101010100101010010101011 @
b111111111 >
b111111111 N
1#
#420
0#
#425
b10111101010101 E
b10111101010101 G
b111000 M
10
1,
0+
b100 9
b1110001010101001110010 @
b10101010 >
b10101010 N
b110 :
1#
#430
0#
#435
b10101 M
b101010100000000000000 @
b10000000000000 ?
1+
1(
0,
00
b101 9
b10111111111111 E
b10111111111111 G
b100000000000000 A
b100000000000000 K
b100000000000000 L
0C
b100 :
b10111101010101 !
b10111101010101 )
b10111101010101 ;
b10111101010101 B
b10111101010101 I
b10 D
b10 F
b10 J
1#
#440
0#
#445
b100000000000000 ?
b10111101101010 E
b10111101101010 G
b101 M
1+
0(
b110 9
b1010100000000000000 @
b10101 >
b10101 N
b101 :
1#
#450
0#
#455
10
1,
0+
b100 9
b10111101011010 E
b10111101011010 G
b1 M
b110 :
b10100000000000000 @
b101 >
b101 N
1#
#460
0#
#465
b0 M
b1010000000000000 @
b10000000000000 ?
b11001100110011 A
b11001100110011 K
b11001100110011 L
1C
b10111101010101 E
b10111101010101 G
1+
1(
0,
00
b101 9
b11 D
b11 F
b11 J
b10111101011010 !
b10111101011010 )
b10111101011010 ;
b10111101011010 B
b10111101011010 I
b100 :
1#
#470
0#
#475
b11001100110011 ?
1+
0(
b110 9
b10111101011010 E
b10111101011010 G
b101 :
b0 @
b0 >
b0 N
1#
#480
0#
#485
10
1,
0+
b100 9
b110 :
1#
#490
0#
#495
b10000000000000 ?
1+
1(
0,
00
b101 9
b10101010101010 A
b10101010101010 K
b10101010101010 L
0C
b100 :
b100 D
b100 F
b100 J
1#
#500
0#
#505
b10101010101010 ?
1+
0(
b110 9
b101 :
1#
#510
0#
#515
10
1,
0+
b100 9
b110 :
1#
#520
0#
#525
b10000000000000 ?
b10010010010010 A
b10010010010010 K
b10010010010010 L
1C
1+
1(
0,
00
b101 9
b101 D
b101 F
b101 J
b100 :
1#
#530
0#
#535
b10010010010010 ?
1+
0(
b110 9
b101 :
1#
#540
0#
#545
10
1,
0+
b100 9
b110 :
1#
#550
0#
#555
b10000000000000 ?
1+
1(
0,
00
b101 9
b10000000000000 A
b10000000000000 K
b10000000000000 L
0C
b100 :
b110 D
b110 F
b110 J
1#
#560
0#
#565
1+
0(
b110 9
b101 :
1#
#570
0#
#575
10
1,
0+
b100 9
b110 :
1#
#580
0#
#585
11
b0 A
b0 K
b0 L
1C
1+
1(
0,
00
b101 9
b111 D
b111 F
b111 J
b100 :
1#
#590
0#
#595
b0 ?
1+
0(
b110 9
b101 :
1#
#600
0#
#605
10
1,
0+
b0 9
b110 :
1#
#610
0#
#615
b1000000000000000 ?
01
1"
0,
00
b1000000000000000 A
b1000000000000000 K
b1000000000000000 L
0C
b0 :
b0 D
b0 F
b0 J
1#
#620
0#
#625
1#
#630
0#
#635
1#
#640
0#
#645
1#
#650
0#
#655
b0 E
b0 G
b0 !
b0 )
b0 ;
b0 B
b0 I
b0 H
b0 =
b0 Q
1#
1$
#660
0#
#665
b1 :
1#
b1 9
0"
1%
b100000000000000 &
b100000000000000 '
b100000000000000 <
b100000000000000 O
0$
#670
0#
#675
1*
b10 :
1#
b11 9
0%
#680
0#
#685
1/
1.
1-
0*
b100 9
b11 :
b100000000000000 H
b100000000000000 =
b100000000000000 Q
1#
#690
0#
#695
b100000000000000 ?
b11111111111111 M
b10011111111111111 E
b10011111111111111 G
1+
1(
0-
0.
0/
b101 9
b111111111111111100000000000000 @
b1111111111111111 >
b1111111111111111 N
b100000000000000 !
b100000000000000 )
b100000000000000 ;
b100000000000000 B
b100000000000000 I
b100 :
1#
#700
0#
#705
b1000000000000000 ?
1+
0(
b110 9
b111111111111111 E
b111111111111111 G
b1111111111111 M
b101 :
b11111111111111000000000000000 @
b11111111111111 >
b11111111111111 N
1#
#710
0#
#715
b101111111111111 E
b101111111111111 G
b111111111111 M
10
1,
0+
b100 9
b1111111111111000000000000000 @
b1111111111111 >
b1111111111111 N
b110 :
1#
#720
0#
#725
b11111111111 M
b111111111111100000000000000 @
b100000000000000 ?
1+
1(
0,
00
b101 9
b100000000000000 E
b100000000000000 G
b101010101010101 A
b101010101010101 K
b101010101010101 L
1C
b100 :
b101111111111111 !
b101111111111111 )
b101111111111111 ;
b101111111111111 B
b101111111111111 I
b1 D
b1 F
b1 J
1#
#730
0#
#735
b101010101010101 ?
b101100000000000 E
b101100000000000 G
b1010101010 M
1+
0(
b110 9
b10101010100101001010101011 @
b11111111111 >
b11111111111 N
b101 :
1#
#740
0#
#745
10
1,
0+
b100 9
b101110101010101 E
b101110101010101 G
b11100011 M
b110 :
b111000110101010001110010 @
b1010101010 >
b1010101010 N
1#
#750
0#
#755
b10101010 M
b101010101000000000000000 @
b100000000000000 ?
b100000000000000 A
b100000000000000 K
b100000000000000 L
0C
b101111111111111 E
b101111111111111 G
1+
1(
0,
00
b101 9
b10 D
b10 F
b10 J
b101110101010101 !
b101110101010101 )
b101110101010101 ;
b101110101010101 B
b101110101010101 I
b100 :
1#
#760
0#
#765
1+
0(
b110 9
b101110111111111 E
b101110111111111 G
b101010 M
b101 :
b1010101000000000000000 @
b10101010 >
b10101010 N
1#
#770
0#
#775
b101110101111111 E
b101110101111111 G
b1010 M
10
1,
0+
b100 9
b10101000000000000000 @
b101010 >
b101010 N
b110 :
1#
#780
0#
#785
1+
1(
0,
00
b101 9
b101110101010101 E
b101110101010101 G
b11001100110011 A
b11001100110011 K
b11001100110011 L
1C
b100 :
b101110101111111 !
b101110101111111 )
b101110101111111 ;
b101110101111111 B
b101110101111111 I
b11 D
b11 F
b11 J
1#
#790
0#
#795
b11001100110011 ?
b101110101110101 E
b101110101110101 G
b1 M
1+
0(
b110 9
b11111111111111110 @
b1010 >
b1010 N
b101 :
1#
#800
0#
#805
10
1,
0+
b100 9
b101110101111110 E
b101110101111110 G
b0 M
b110 :
b11001100110011 @
b1 >
b1 N
1#
#810
0#
#815
b100000000000000 @
b100000000000000 ?
b10101010101010 A
b10101010101010 K
b10101010101010 L
0C
b101110101111111 E
b101110101111111 G
1+
1(
0,
00
b101 9
b100 D
b100 F
b100 J
b101110101111110 !
b101110101111110 )
b101110101111110 ;
b101110101111110 B
b101110101111110 I
b100 :
1#
#820
0#
#825
b10101010101010 ?
1+
0(
b110 9
b101110101111110 E
b101110101111110 G
b101 :
b0 @
b0 >
b0 N
1#
#830
0#
#835
10
1,
0+
b100 9
b110 :
1#
#840
0#
#845
b100000000000000 ?
1+
1(
0,
00
b101 9
b10010010010010 A
b10010010010010 K
b10010010010010 L
1C
b100 :
b101 D
b101 F
b101 J
1#
#850
0#
#855
b10010010010010 ?
1+
0(
b110 9
b101 :
1#
#860
0#
#865
10
1,
0+
b100 9
b110 :
1#
#870
0#
#875
b100000000000000 ?
b10000000000000 A
b10000000000000 K
b10000000000000 L
0C
1+
1(
0,
00
b101 9
b110 D
b110 F
b110 J
b100 :
1#
#880
0#
#885
b10000000000000 ?
1+
0(
b110 9
b101 :
1#
#890
0#
#895
10
1,
0+
b100 9
b110 :
1#
#900
0#
#905
b100000000000000 ?
11
1+
1(
0,
00
b101 9
b0 A
b0 K
b0 L
1C
b100 :
b111 D
b111 F
b111 J
1#
#910
0#
#915
b0 ?
1+
0(
b110 9
b101 :
1#
#920
0#
#925
10
1,
0+
b0 9
b110 :
1#
#930
0#
#935
b1000000000000000 ?
01
b1000000000000000 A
b1000000000000000 K
b1000000000000000 L
0C
1"
0,
00
b0 D
b0 F
b0 J
b0 :
1#
#940
0#
#945
1#
#950
0#
#955
1#
#960
0#
#965
1#
#970
0#
#975
1#
#980
b0 E
b0 G
b0 !
b0 )
b0 ;
b0 B
b0 I
b0 H
b0 =
b0 Q
0#
1$
#985
1#
#990
0#
b1 9
1"
1%
b1000000000000000 &
b1000000000000000 '
b1000000000000000 <
b1000000000000000 O
0$
#995
0"
b1 9
b1 :
1#
#1000
0#
b10 9
0%
#1005
1*
b11 9
b10 :
1#
#1010
0#
#1015
1/
1.
1-
0*
b100 9
b11 :
b1000000000000000 H
b1000000000000000 =
b1000000000000000 Q
1#
#1020
0#
#1025
b111111111111111 M
b10111111111111111 E
b10111111111111111 G
1+
1(
0-
0.
0/
b101 9
b1111111111111111000000000000000 @
b1111111111111111 >
b1111111111111111 N
b1000000000000000 !
b1000000000000000 )
b1000000000000000 ;
b1000000000000000 B
b1000000000000000 I
b100 :
1#
#1030
0#
#1035
1+
0(
b110 9
b1111111111111111 E
b1111111111111111 G
b11111111111111 M
b101 :
b111111111111111000000000000000 @
b111111111111111 >
b111111111111111 N
1#
#1040
0#
#1045
b1011111111111111 E
b1011111111111111 G
b1111111111111 M
10
1,
0+
b100 9
b11111111111111000000000000000 @
b11111111111111 >
b11111111111111 N
b110 :
1#
#1050
0#
#1055
1+
1(
0,
00
b101 9
b1000000000000000 E
b1000000000000000 G
b101010101010101 A
b101010101010101 K
b101010101010101 L
1C
b100 :
b1011111111111111 !
b1011111111111111 )
b1011111111111111 ;
b1011111111111111 B
b1011111111111111 I
b1 D
b1 F
b1 J
1#
#1060
0#
#1065
b101010101010101 ?
b1010000000000000 E
b1010000000000000 G
b101010101010 M
1+
0(
b110 9
b1010101010100100101010101011 @
b1111111111111 >
b1111111111111 N
b101 :
1#
#1070
0#
#1075
10
1,
0+
b100 9
b1011010101010101 E
b1011010101010101 G
b1110001101 M
b110 :
b11100011011111110001110010 @
b101010101010 >
b101010101010 N
1#
#1080
0#
#1085
b10101010101 M
b101010101010000000000000000 @
b1000000000000000 ?
b100000000000000 A
b100000000000000 K
b100000000000000 L
0C
b1011111111111111 E
b1011111111111111 G
1+
1(
0,
00
b101 9
b10 D
b10 F
b10 J
b1011010101010101 !
b1011010101010101 )
b1011010101010101 ;
b1011010101010101 B
b1011010101010101 I
b100 :
1#
#1090
0#
#1095
b100000000000000 ?
1+
0(
b110 9
b1011101010101010 E
b1011101010101010 G
b101010101 M
b101 :
b1010101010100000000000000 @
b10101010101 >
b10101010101 N
1#
#1100
0#
#1105
b1011011010101010 E
b1011011010101010 G
b1010101 M
10
1,
0+
b100 9
b10101010100000000000000 @
b101010101 >
b101010101 N
b110 :
1#
#1110
0#
#1115
b10101010 M
b101010101000000000000000 @
b1000000000000000 ?
1+
1(
0,
00
b101 9
b1011010101010101 E
b1011010101010101 G
b11001100110011 A
b11001100110011 K
b11001100110011 L
1C
b100 :
b1011011010101010 !
b1011011010101010 )
b1011011010101010 ;
b1011011010101010 B
b1011011010101010 I
b11 D
b11 F
b11 J
1#
#1120
0#
#1125
b11001100110011 ?
b1011011000000000 E
b1011011000000000 G
b100001 M
1+
0(
b110 9
b1000011111111111011110 @
b10101010 >
b10101010 N
b101 :
1#
#1130
0#
#1135
10
1,
0+
b100 9
b1011011010001001 E
b1011011010001001 G
b110 M
b110 :
b1101001100110010011 @
b100001 >
b100001 N
1#
#1140
0#
#1145
b10000 M
b100001000000000000000 @
b1000000000000000 ?
b10101010101010 A
b10101010101010 K
b10101010101010 L
0C
b1011011010101010 E
b1011011010101010 G
1+
1(
0,
00
b101 9
b100 D
b100 F
b100 J
b1011011010001001 !
b1011011010001001 )
b1011011010001001 ;
b1011011010001001 B
b1011011010001001 I
b100 :
1#
#1150
0#
#1155
b10101010101010 ?
1+
0(
b110 9
b1011011010011001 E
b1011011010011001 G
b10 M
b101 :
b101010101010100000 @
b10000 >
b10000 N
1#
#1160
0#
#1165
b1011011010001011 E
b1011011010001011 G
b0 M
10
1,
0+
b100 9
b101010101010100 @
b10 >
b10 N
b110 :
1#
#1170
0#
#1175
b1 M
b10000000000000000 @
b1000000000000000 ?
1+
1(
0,
00
b101 9
b1011011010001001 E
b1011011010001001 G
b10010010010010 A
b10010010010010 K
b10010010010010 L
1C
b100 :
b1011011010001011 !
b1011011010001011 )
b1011011010001011 ;
b1011011010001011 B
b1011011010001011 I
b101 D
b101 F
b101 J
1#
#1180
0#
#1185
b10010010010010 ?
b1011011010001010 E
b1011011010001010 G
b0 M
1+
0(
b110 9
b10010010010010 @
b1 >
b1 N
b101 :
1#
#1190
0#
#1195
10
1,
0+
b100 9
b1011011010001011 E
b1011011010001011 G
b110 :
b0 @
b0 >
b0 N
1#
#1200
0#
#1205
b1000000000000000 ?
b10000000000000 A
b10000000000000 K
b10000000000000 L
0C
1+
1(
0,
00
b101 9
b110 D
b110 F
b110 J
b100 :
1#
#1210
0#
#1215
b10000000000000 ?
1+
0(
b110 9
b101 :
1#
#1220
0#
#1225
10
1,
0+
b100 9
b110 :
1#
#1230
0#
#1235
b1000000000000000 ?
11
1+
1(
0,
00
b101 9
b0 A
b0 K
b0 L
1C
b100 :
b111 D
b111 F
b111 J
1#
#1240
0#
#1245
b0 ?
1+
0(
b110 9
b101 :
1#
#1250
0#
#1255
10
1,
0+
b0 9
b110 :
1#
#1260
0#
#1265
b1000000000000000 ?
01
b1000000000000000 A
b1000000000000000 K
b1000000000000000 L
0C
1"
0,
00
b0 D
b0 F
b0 J
b0 :
1#
#1270
0#
#1275
1#
#1280
0#
#1285
1#
#1290
0#
#1295
1#
#1300
0#
#1305
b0 E
b0 G
b0 H
b0 =
b0 Q
b0 !
b0 )
b0 ;
b0 B
b0 I
1#
1$
#1310
0#
#1315
b1 :
1#
b1 9
0"
1%
b1111111111111111 &
b1111111111111111 '
b1111111111111111 <
b1111111111111111 O
0$
#1320
0#
#1325
1*
b10 :
1#
b11 9
0%
#1330
0#
#1335
1/
1.
1-
0*
b100 9
b1111111111111111 H
b1111111111111111 =
b1111111111111111 Q
b11 :
1#
#1340
0#
#1345
b1111111111111111 ?
1+
1(
0-
0.
0/
b101 9
b11111111111111110 E
b11111111111111110 G
b1111111111111110 M
b100 :
b1111111111111111 !
b1111111111111111 )
b1111111111111111 ;
b1111111111111111 B
b1111111111111111 I
b11111111111111100000000000000001 @
b1111111111111111 >
b1111111111111111 N
1#
#1350
0#
#1355
b1000000000000000 ?
b11111111111111101 E
b11111111111111101 G
b111111111111111 M
1+
0(
b110 9
b1111111111111110000000000000000 @
b1111111111111110 >
b1111111111111110 N
b101 :
1#
#1360
0#
