sinCU.v
// controller unit module for sin (state machine)
module sinCU (input clk, rst, start, cnt8,
  output reg done, ldX, initT1, initS1, ldT, ldS, init0, cntUp, selXR);

  // states
  reg [2:0] pstate, nstate;
  parameter IDLE = 0, STARTING = 1, GETINPUT = 2, GETINPUT2 = 3, MULT1 = 4, MULT2 = 5, ADD = 6;

  // registers
  always @(posedge clk, posedge rst) begin
    if (rst == 1)
      pstate <= IDLE;
    else
      pstate <= nstate;
  end

  // combinational part
  always @(pstate, start, cnt8) begin
    nstate = IDLE; // default
    done = 0;
    {ldX, initT1, initS1, ldT, ldS, init0, cntUp, selXR} = 8'b0;
    // 1. State: IDLE
    if (pstate == IDLE) begin nstate = (start == 1) ? STARTING : IDLE;
      done = 1;
    end
    // 2. State: STARTING
    if (pstate == STARTING) begin 
      nstate = (start == 0) ? GETINPUT: STARTING;
    end
    // 3. State: GETINPUT
    if (pstate == GETINPUT) begin 
      nstate = GETINPUT2;
      ldX = 1; // new extra state for delay
    end
    // 4. State: GETINPUT2
    if (pstate == GETINPUT2) begin 
      nstate = MULT1;
      initT1 = 1; initS1 = 1; init0 = 1; // sin = xin, term = xin
    end
    // 5. State: MULT1
    if (pstate == MULT1) begin 
      nstate = MULT2;
      selXR = 1; ldT = 1;
    end
    // 6. State: MULT2
    if (pstate == MULT2) begin 
      nstate = ADD;
      ldT = 1;
    end
    // 7. State: ADD 
    if (pstate == ADD) begin 
      nstate = (cnt8 == 1)? IDLE : MULT1;
      ldS = 1; cntUp = 1;
    end
  end

endmodule

sinReg18.v
// 18 bit registers for sin
module sinReg18 (input clk, rst, init1, load, input [17:0] initS, input [17:0] in, output reg [17:0] out);
  always @ (posedge clk, posedge rst) begin
    if (rst == 1)
      out <= 0;
    else begin
      if (init1 == 1)
        out <= initS;
      else begin
        if (load == 1)
          out <= in;
      end
    end
  end
endmodule

sinReg16.v
// 16-bit register with initialization for sin
module sinReg16 (input clk, rst, init1, load, input [15:0] initVal, 
  input [15:0] in, output reg [15:0] out);
  always @ (posedge clk, posedge rst) begin
    if (rst == 1)
      out <= 0;
    else begin
      if (init1 == 1)
        out <= initVal;
      else begin
        if (load == 1)
          out <= in;
      end
    end
  end
endmodule

reg16.v
// 16 bit registers for input busses
module reg16 (input clk, rst, init1, load, input [15:0] in, output reg [15:0] out);
  always @ (posedge clk, posedge rst) begin
    if (rst == 1)
      out <= 0;
    else begin
      if (init1 == 1)
        out <= 16'hFFFF;
      else begin
        if (load == 1)
          out <= in;
      end
    end
  end
endmodule

sinLUT.v
// look up table module for sin 
module sinLUT (input [2:0]addr, output [15:0] data);
  reg [15:0] dataOut;
  always @(addr) begin
    case(addr)
      0: dataOut = 16'hFFFF; // 1/1!
      1: dataOut = 16'h2AAB; // 1/3!
      2: dataOut = 16'h0222; // 1/5!
      3: dataOut = 16'h000D; // 1/7!
      4: dataOut = 16'h0000; // 1/9! ~= 0
      5: dataOut = 16'h0000; // 1/11! ~= 0
      6: dataOut = 16'h0000; // 1/13! ~= 0
      7: dataOut = 16'h0000; // 1/15! ~= 0
    endcase
  end
  assign data = dataOut;
endmodule

cntReg.v
// 3-bit counter module
module cntReg (input clk, rst, cntUp, init0, output reg [2:0] cnt);
  always @ (posedge clk, posedge rst) begin
    if (rst == 1)
      cnt <= 0;
    else begin
      if (init0 == 1)
        cnt <= 0;
      else begin
        if (cntUp == 1)
          cnt <= cnt + 1;
      end
    end
  end
endmodule

sinDU.v
// datapath module for sin 
module sinDU (input clk, rst, cntUp, init0, ldX, ldT, initT1, ldS, initS1, selXR,
  input [15:0] xBus, output cnt8, output [17:0] rBus);

  // mid-level signals
  wire [2:0] cntOut;
  wire [17:0] sOut, addOut;
  wire [15:0] lutOut, xOut, tOut, muxOut;
  wire [31:0] mulOut;
  wire isOdd;
  wire [31:0] xSquared;

  // module instantiations 
  cntReg cntr(clk, rst, cntUp, init0, cntOut);
  sinLUT lut(cntOut, lutOut);
  reg16 xReg(clk, rst, 1'b0, ldX, xBus, xOut); // no need to initialize
  sinReg16 tReg(clk, rst, initT1, ldT, xOut, mulOut[31:16], tOut); // new
  sinReg18 sReg(clk, rst, initS1, ldS, {2'b00, xOut}, addOut, sOut); // new

  // add sub assignment: if it's odd cntOut[0] would be 1
  assign isOdd = cntOut[0]; // new

  // output assigning
  assign xSquared = xOut * xOut; // new
  assign muxOut = (selXR == 1) ? xSquared[31:16] : lutOut; // mux
  assign mulOut = (muxOut * tOut); 
  assign addOut = (isOdd == 1) ? sOut - {2'b00, tOut} : sOut + {2'b00, tOut}; // new

  // final output
  assign rBus = sOut;
  assign cnt8 = (cntOut == 3'b111) ? 1 : 0;

endmodule

sinTop.v
// top module for sin 
module sinTop (input clk, rst, start, input [15:0] xBus, output [17:0] rBus, output done);
  // 1-bit wires 
  wire cntUp, init0, ldX, ldT, initT1, initS1, selXR, cnt8;

  // datapath
  sinDU du(clk, rst, cntUp, init0, ldX, ldT, initT1, ldS, initS1, selXR, xBus, cnt8, rBus);

  // controller
  sinCU cp(clk, rst, start, cnt8, done, ldX, initT1, initS1, ldT, ldS, init0, cntUp, selXR);

endmodule

sinTB.v
// test bech for sin module
`timescale 1ns/1ns

module sinTB ();
  reg clk = 0;
  reg rst = 0;
  reg start = 0;
  reg [15:0] xBus;
  wire done;
  wire [17:0] rBus;

  sinTop sin(clk, rst, start, xBus, rBus, done);

  // generating clock behaviour
  always #5 clk <= ~clk;
  initial begin
    // Dump waveform data to a file.
    $dumpfile("sin_sim.vcd");
    $dumpvars(0, sinTB);

    // x = 0 rad => sin(x) = 0.0 rad
    #5;
    rst = 1;

    #5;
    #5;
    rst = 0;
    xBus = 0;
    start = 1;

    #5;
    #5;
    start = 0;

    #300;

    // x = 0.125 rad => sin(x) = 0.12467 rad
    #5;
    rst = 1;

    #5;
    #5;
    rst = 0;
    xBus = 16'h2000; // 0.125
    start = 1;

    #5;
    #5;
    start = 0;

    #300;

    // x = 0.25 rad => sin(x) = 0.24740 rad
    #5;
    rst = 1;

    #5;
    #5;
    rst = 0;
    xBus = 16'h4000; // 0.25
    start = 1;

    #5;
    #5;
    start = 0;

    #300;
    // x = 0.5 rad => sin(x) = 0.479425 rad
    #5;
    rst = 1;

    #5;
    #5;
    rst = 0;
    xBus = 16'h8000; // 0.5
    start = 1;

    #5;
    #5;
    start = 0;

    #300;
    // x = 1 rad => sin(x) = 0.84147 rad
    #5;
    rst = 1;

    #5;
    #5;
    rst = 0;
    xBus = 16'hFFFF; // 1 
    start = 1;

    #5;
    #5;
    start = 0;

    #300;

    // x = 1.5 rad => sin(1.5) ≈ 0.99749
    #5; rst = 1;
    #5; #5; rst = 0; xBus = 16'h18000; start = 1;
    #5; #5; start = 0;
    #300;

    // x = 2 rad => sin(2) ≈ 0.90929
    #5; rst = 1;
    #5; #5; rst = 0; xBus = 16'h20000; start = 1;
    #5; #5; start = 0;
    #300;

    // x = 2.5 rad => sin(2.5) ≈ 0.59847
    #5; rst = 1;
    #5; #5; rst = 0; xBus = 16'h28000; start = 1;
    #5; #5; start = 0;
    #300;

    // x = 3 rad => sin(3) ≈ 0.14112
    #5; rst = 1;
    #5; #5; rst = 0; xBus = 16'h30000; start = 1;
    #5; #5; start = 0;
    #300;

    // x = 3.5 rad => sin(3.5) ≈ -0.35078
    #5; rst = 1;
    #5; #5; rst = 0; xBus = 16'h38000; start = 1;
    #5; #5; start = 0;
    #300;

    $finish; 
  end

endmodule

sin_sim.vcd
$date
	Fri Feb  7 14:46:57 2025
$end
$version
	Icarus Verilog
$end
$timescale
	1ns
$end
$scope module sinTB $end
$var wire 18 ! rBus [17:0] $end
$var wire 1 " done $end
$var reg 1 # clk $end
$var reg 1 $ rst $end
$var reg 1 % start $end
$var reg 16 & xBus [15:0] $end
$scope module sin $end
$var wire 1 # clk $end
$var wire 1 $ rst $end
$var wire 1 % start $end
$var wire 16 ' xBus [15:0] $end
$var wire 1 ( selXR $end
$var wire 18 ) rBus [17:0] $end
$var wire 1 * ldX $end
$var wire 1 + ldT $end
$var wire 1 , ldS $end
$var wire 1 - initT1 $end
$var wire 1 . initS1 $end
$var wire 1 / init0 $end
$var wire 1 " done $end
$var wire 1 0 cntUp $end
$var wire 1 1 cnt8 $end
$scope module cp $end
$var wire 1 # clk $end
$var wire 1 $ rst $end
$var wire 1 % start $end
$var wire 1 1 cnt8 $end
$var parameter 32 2 ADD $end
$var parameter 32 3 GETINPUT $end
$var parameter 32 4 GETINPUT2 $end
$var parameter 32 5 IDLE $end
$var parameter 32 6 MULT1 $end
$var parameter 32 7 MULT2 $end
$var parameter 32 8 STARTING $end
$var reg 1 0 cntUp $end
$var reg 1 " done $end
$var reg 1 / init0 $end
$var reg 1 . initS1 $end
$var reg 1 - initT1 $end
$var reg 1 , ldS $end
$var reg 1 + ldT $end
$var reg 1 * ldX $end
$var reg 3 9 nstate [2:0] $end
$var reg 3 : pstate [2:0] $end
$var reg 1 ( selXR $end
$upscope $end
$scope module du $end
$var wire 1 # clk $end
$var wire 1 0 cntUp $end
$var wire 1 / init0 $end
$var wire 1 . initS1 $end
$var wire 1 - initT1 $end
$var wire 1 , ldS $end
$var wire 1 + ldT $end
$var wire 1 * ldX $end
$var wire 18 ; rBus [17:0] $end
$var wire 1 $ rst $end
$var wire 1 ( selXR $end
$var wire 16 < xBus [15:0] $end
$var wire 32 = xSquared [31:0] $end
$var wire 16 > xOut [15:0] $end
$var wire 16 ? tOut [15:0] $end
$var wire 18 @ sOut [17:0] $end
$var wire 16 A muxOut [15:0] $end
$var wire 32 B mulOut [31:0] $end
$var wire 16 C lutOut [15:0] $end
$var wire 1 D isOdd $end
$var wire 3 E cntOut [2:0] $end
$var wire 1 1 cnt8 $end
$var wire 18 F addOut [17:0] $end
$scope module cntr $end
$var wire 1 # clk $end
$var wire 1 0 cntUp $end
$var wire 1 / init0 $end
$var wire 1 $ rst $end
$var reg 3 G cnt [2:0] $end
$upscope $end
$scope module lut $end
$var wire 3 H addr [2:0] $end
$var wire 16 I data [15:0] $end
$var reg 16 J dataOut [15:0] $end
$upscope $end
$scope module sReg $end
$var wire 1 # clk $end
$var wire 18 K in [17:0] $end
$var wire 1 . init1 $end
$var wire 18 L initS [17:0] $end
$var wire 1 , load $end
$var wire 1 $ rst $end
$var reg 18 M out [17:0] $end
$upscope $end
$scope module tReg $end
$var wire 1 # clk $end
$var wire 16 N in [15:0] $end
$var wire 1 - init1 $end
$var wire 1 + load $end
$var wire 1 $ rst $end
$var wire 16 O initVal [15:0] $end
$var reg 16 P out [15:0] $end
$upscope $end
$scope module xReg $end
$var wire 1 # clk $end
$var wire 16 Q in [15:0] $end
$var wire 1 R init1 $end
$var wire 1 * load $end
$var wire 1 $ rst $end
$var reg 16 S out [15:0] $end
$upscope $end
$upscope $end
$upscope $end
$upscope $end
$enddefinitions $end
$comment Show the parameter values. $end
$dumpall
b1 8
b101 7
b100 6
b0 5
b11 4
b10 3
b110 2
$end
#0
$dumpvars
bx S
0R
bx Q
bx P
bx O
bx N
bx M
b0xxxxxxxxxxxxxxxx L
bx K
bx J
bx I
bx H
bx G
bx F
bx E
xD
bx C
bx B
bx A
bx @
bx ?
bx >
bx =
bx <
bx ;
bx :
b0 9
x1
00
0/
0.
0-
0,
0+
0*
bx )
0(
bx '
bx &
0%
0$
0#
0"
bx !
$end
#5
b0 N
b0 B
b1111111111111111 A
01
b1111111111111111 C
b1111111111111111 I
b1111111111111111 J
0D
b0 F
b0 K
1"
b0 E
b0 G
b0 H
b0 =
b0 L
b0 >
b0 O
b0 S
b0 ?
b0 P
b0 !
b0 )
b0 ;
b0 @
b0 M
b0 :
1#
1$
#10
0#
#15
b1 :
1#
b1 9
0"
1%
b0 &
b0 '
b0 <
b0 Q
0$
#20
0#
#25
1*
b10 :
1#
b11 9
0%
#30
0#
#35
1/
1.
1-
0*
b100 9
b11 :
1#
#40
0#
#45
b0 A
1+
1(
0-
0.
0/
b101 9
b100 :
1#
#50
0#
#55
b1111111111111111 A
1+
0(
b110 9
b101 :
1#
#60
0#
#65
10
1,
0+
b100 9
b110 :
1#
#70
0#
#75
b0 A
b10101010101011 C
b10101010101011 I
b10101010101011 J
1D
1+
1(
0,
00
b101 9
b1 E
b1 G
b1 H
b100 :
1#
#80
0#
#85
b10101010101011 A
1+
0(
b110 9
b101 :
1#
#90
0#
#95
10
1,
0+
b100 9
b110 :
1#
#100
0#
#105
b0 A
1+
1(
0,
00
b101 9
b1000100010 C
b1000100010 I
b1000100010 J
0D
b100 :
b10 E
b10 G
b10 H
1#
#110
0#
#115
b1000100010 A
1+
0(
b110 9
b101 :
1#
#120
0#
#125
10
1,
0+
b100 9
b110 :
1#
#130
0#
#135
b0 A
b1101 C
b1101 I
b1101 J
1D
1+
1(
0,
00
b101 9
b11 E
b11 G
b11 H
b100 :
1#
#140
0#
#145
b1101 A
1+
0(
b110 9
b101 :
1#
#150
0#
#155
10
1,
0+
b100 9
b110 :
1#
#160
0#
#165
b0 A
1+
1(
0,
00
b101 9
b0 C
b0 I
b0 J
0D
b100 :
b100 E
b100 G
b100 H
1#
#170
0#
#175
1+
0(
b110 9
b101 :
1#
#180
0#
#185
10
1,
0+
b100 9
b110 :
1#
#190
0#
#195
1D
1+
1(
0,
00
b101 9
b101 E
b101 G
b101 H
b100 :
1#
#200
0#
#205
1+
0(
b110 9
b101 :
1#
#210
0#
#215
10
1,
0+
b100 9
b110 :
1#
#220
0#
#225
1+
1(
0,
00
b101 9
0D
b100 :
b110 E
b110 G
b110 H
1#
#230
0#
#235
1+
0(
b110 9
b101 :
1#
#240
0#
#245
10
1,
0+
b100 9
b110 :
1#
#250
0#
#255
11
1D
1+
1(
0,
00
b101 9
b111 E
b111 G
b111 H
b100 :
1#
#260
0#
#265
1+
0(
b110 9
b101 :
1#
#270
0#
#275
10
1,
0+
b0 9
b110 :
1#
#280
0#
#285
b1111111111111111 A
01
1"
0,
00
b1111111111111111 C
b1111111111111111 I
b1111111111111111 J
0D
b0 :
b0 E
b0 G
b0 H
1#
#290
0#
#295
1#
#300
0#
#305
1#
#310
0#
#315
1#
#320
0#
#325
1#
#330
0#
1$
#335
1#
#340
0#
b1 9
1"
1%
b10000000000000 &
b10000000000000 '
b10000000000000 <
b10000000000000 Q
0$
#345
0"
b1 9
b1 :
1#
#350
0#
b10 9
0%
#355
1*
b11 9
b10 :
1#
#360
0#
#365
1/
1.
1-
0*
b100 9
b100000000000000000000000000 =
b10000000000000 L
b10000000000000 >
b10000000000000 O
b10000000000000 S
b11 :
1#
#370
0#
#375
b10000000000 A
1+
1(
0-
0.
0/
b101 9
b100000000000000 F
b100000000000000 K
b10000000 N
b100 :
b10000000000000 !
b10000000000000 )
b10000000000000 ;
b10000000000000 @
b10000000000000 M
b100000000000000000000000 B
b10000000000000 ?
b10000000000000 P
1#
#380
0#
#385
b1111111111111111 A
b10000010000000 F
b10000010000000 K
b1111111 N
1+
0(
b110 9
b11111111111111110000000 B
b10000000 ?
b10000000 P
b101 :
1#
#390
0#
#395
10
1,
0+
b100 9
b10000001111111 F
b10000001111111 K
b1111110 N
b110 :
b11111101111111110000001 B
b1111111 ?
b1111111 P
1#
#400
0#
#405
b1 N
b11111110000000000 B
b10000000000 A
b10101010101011 C
b10101010101011 I
b10101010101011 J
1D
b10000000000000 F
b10000000000000 K
1+
1(
0,
00
b101 9
b1 E
b1 G
b1 H
b10000001111111 !
b10000001111111 )
b10000001111111 ;
b10000001111111 @
b10000001111111 M
b100 :
1#
#410
0#
#415
b10101010101011 A
1+
0(
b110 9
b10000001111110 F
b10000001111110 K
b0 N
b101 :
b10101010101011 B
b1 ?
b1 P
1#
#420
0#
#425
b10000001111111 F
b10000001111111 K
10
1,
0+
b100 9
b0 B
b0 ?
b0 P
b110 :
1#
#430
0#
#435
b10000000000 A
1+
1(
0,
00
b101 9
b1000100010 C
b1000100010 I
b1000100010 J
0D
b100 :
b10 E
b10 G
b10 H
1#
#440
0#
#445
b1000100010 A
1+
0(
b110 9
b101 :
1#
#450
0#
#455
10
1,
0+
b100 9
b110 :
1#
#460
0#
#465
b10000000000 A
b1101 C
b1101 I
b1101 J
1D
1+
1(
0,
00
b101 9
b11 E
b11 G
b11 H
b100 :
1#
#470
0#
#475
b1101 A
1+
0(
b110 9
b101 :
1#
#480
0#
#485
10
1,
0+
b100 9
b110 :
1#
#490
0#
#495
b10000000000 A
1+
1(
0,
00
b101 9
b0 C
b0 I
b0 J
0D
b100 :
b100 E
b100 G
b100 H
1#
#500
0#
#505
b0 A
1+
0(
b110 9
b101 :
1#
#510
0#
#515
10
1,
0+
b100 9
b110 :
1#
#520
0#
#525
b10000000000 A
1D
1+
1(
0,
00
b101 9
b101 E
b101 G
b101 H
b100 :
1#
#530
0#
#535
b0 A
1+
0(
b110 9
b101 :
1#
#540
0#
#545
10
1,
0+
b100 9
b110 :
1#
#550
0#
#555
b10000000000 A
1+
1(
0,
00
b101 9
0D
b100 :
b110 E
b110 G
b110 H
1#
#560
0#
#565
b0 A
1+
0(
b110 9
b101 :
1#
#570
0#
#575
10
1,
0+
b100 9
b110 :
1#
#580
0#
#585
11
b10000000000 A
1D
1+
1(
0,
00
b101 9
b111 E
b111 G
b111 H
b100 :
1#
#590
0#
#595
b0 A
1+
0(
b110 9
b101 :
1#
#600
0#
#605
10
1,
0+
b0 9
b110 :
1#
#610
0#
#615
b1111111111111111 A
01
1"
0,
00
b1111111111111111 C
b1111111111111111 I
b1111111111111111 J
0D
b0 :
b0 E
b0 G
b0 H
1#
#620
0#
#625
1#
#630
0#
#635
1#
#640
0#
#645
1#
#650
0#
#655
b0 F
b0 K
b0 !
b0 )
b0 ;
b0 @
b0 M
b0 =
b0 L
b0 >
b0 O
b0 S
1#
1$
#660
0#
#665
b1 :
1#
b1 9
0"
1%
b100000000000000 &
b100000000000000 '
b100000000000000 <
b100000000000000 Q
0$
#670
0#
#675
1*
b10 :
1#
b11 9
0%
#680
0#
#685
1/
1.
1-
0*
b100 9
b11 :
b10000000000000000000000000000 =
b100000000000000 L
b100000000000000 >
b100000000000000 O
b100000000000000 S
1#
#690
0#
#695
b1000000000000 A
b10000000000 N
b1000000000000000 F
b1000000000000000 K
1+
1(
0-
0.
0/
b101 9
b100000000000000000000000000 B
b100000000000000 ?
b100000000000000 P
b100000000000000 !
b100000000000000 )
b100000000000000 ;
b100000000000000 @
b100000000000000 M
b100 :
1#
#700
0#
#705
b1111111111111111 A
1+
0(
b110 9
b100010000000000 F
b100010000000000 K
b1111111111 N
b101 :
b11111111111111110000000000 B
b10000000000 ?
b10000000000 P
1#
#710
0#
#715
b100001111111111 F
b100001111111111 K
b1111111110 N
10
1,
0+
b100 9
b11111111101111110000000001 B
b1111111111 ?
b1111111111 P
b110 :
1#
#720
0#
#725
b111111 N
b1111111111000000000000 B
b1000000000000 A
1+
1(
0,
00
b101 9
b100000000000000 F
b100000000000000 K
b10101010101011 C
b10101010101011 I
b10101010101011 J
1D
b100 :
b100001111111111 !
b100001111111111 )
b100001111111111 ;
b100001111111111 @
b100001111111111 M
b1 E
b1 G
b1 H
1#
#730
0#
#735
b10101010101011 A
b100001111000000 F
b100001111000000 K
b1010 N
1+
0(
b110 9
b10101000000000010101 B
b111111 ?
b111111 P
b101 :
1#
#740
0#
#745
10
1,
0+
b100 9
b100001111110101 F
b100001111110101 K
b1 N
b110 :
b11010101010101110 B
b1010 ?
b1010 P
1#
#750
0#
#755
b0 N
b1010000000000000 B
b1000000000000 A
b1000100010 C
b1000100010 I
b1000100010 J
0D
b100001111111111 F
b100001111111111 K
1+
1(
0,
00
b101 9
b10 E
b10 G
b10 H
b100001111110101 !
b100001111110101 )
b100001111110101 ;
b100001111110101 @
b100001111110101 M
b100 :
1#
#760
0#
#765
b1000100010 A
1+
0(
b110 9
b100001111110101 F
b100001111110101 K
b101 :
b0 B
b0 ?
b0 P
1#
#770
0#
#775
10
1,
0+
b100 9
b110 :
1#
#780
0#
#785
b1000000000000 A
1+
1(
0,
00
b101 9
b1101 C
b1101 I
b1101 J
1D
b100 :
b11 E
b11 G
b11 H
1#
#790
0#
#795
b1101 A
1+
0(
b110 9
b101 :
1#
#800
0#
#805
10
1,
0+
b100 9
b110 :
1#
#810
0#
#815
b1000000000000 A
b0 C
b0 I
b0 J
0D
1+
1(
0,
00
b101 9
b100 E
b100 G
b100 H
b100 :
1#
#820
0#
#825
b0 A
1+
0(
b110 9
b101 :
1#
#830
0#
#835
10
1,
0+
b100 9
b110 :
1#
#840
0#
#845
b1000000000000 A
1+
1(
0,
00
b101 9
1D
b100 :
b101 E
b101 G
b101 H
1#
#850
0#
#855
b0 A
1+
0(
b110 9
b101 :
1#
#860
0#
#865
10
1,
0+
b100 9
b110 :
1#
#870
0#
#875
b1000000000000 A
0D
1+
1(
0,
00
b101 9
b110 E
b110 G
b110 H
b100 :
1#
#880
0#
#885
b0 A
1+
0(
b110 9
b101 :
1#
#890
0#
#895
10
1,
0+
b100 9
b110 :
1#
#900
0#
#905
b1000000000000 A
11
1+
1(
0,
00
b101 9
1D
b100 :
b111 E
b111 G
b111 H
1#
#910
0#
#915
b0 A
1+
0(
b110 9
b101 :
1#
#920
0#
#925
10
1,
0+
b0 9
b110 :
1#
#930
0#
#935
b1111111111111111 A
01
b1111111111111111 C
b1111111111111111 I
b1111111111111111 J
0D
1"
0,
00
b0 E
b0 G
b0 H
b0 :
1#
#940
0#
#945
1#
#950
0#
#955
1#
#960
0#
#965
1#
#970
0#
#975
1#
#980
b0 F
b0 K
b0 !
b0 )
b0 ;
b0 @
b0 M
b0 =
b0 L
b0 >
b0 O
b0 S
0#
1$
#985
1#
#990
0#
b1 9
1"
1%
b1000000000000000 &
b1000000000000000 '
b1000000000000000 <
b1000000000000000 Q
0$
#995
0"
b1 9
b1 :
1#
#1000
0#
b10 9
0%
#1005
1*
b11 9
b10 :
1#
#1010
0#
#1015
1/
1.
1-
0*
b100 9
b11 :
b1000000000000000000000000000000 =
b1000000000000000 L
b1000000000000000 >
b1000000000000000 O
b1000000000000000 S
1#
#1020
0#
#1025
b100000000000000 A
b10000000000000 N
b10000000000000000 F
b10000000000000000 K
1+
1(
0-
0.
0/
b101 9
b100000000000000000000000000000 B
b1000000000000000 ?
b1000000000000000 P
b1000000000000000 !
b1000000000000000 )
b1000000000000000 ;
b1000000000000000 @
b1000000000000000 M
b100 :
1#
#1030
0#
#1035
b1111111111111111 A
1+
0(
b110 9
b1010000000000000 F
b1010000000000000 K
b1111111111111 N
b101 :
b11111111111111110000000000000 B
b10000000000000 ?
b10000000000000 P
1#
#1040
0#
#1045
b1001111111111111 F
b1001111111111111 K
b1111111111110 N
10
1,
0+
b100 9
b11111111111101110000000000001 B
b1111111111111 ?
b1111111111111 P
b110 :
1#
#1050
0#
#1055
b11111111111 N
b111111111111100000000000000 B
b100000000000000 A
1+
1(
0,
00
b101 9
b1000000000000000 F
b1000000000000000 K
b10101010101011 C
b10101010101011 I
b10101010101011 J
1D
b100 :
b1001111111111111 !
b1001111111111111 )
b1001111111111111 ;
b1001111111111111 @
b1001111111111111 M
b1 E
b1 G
b1 H
1#
#1060
0#
#1065
b10101010101011 A
b1001100000000000 F
b1001100000000000 K
b101010101 N
1+
0(
b110 9
b1010101010010110101010101 B
b11111111111 ?
b11111111111 P
b101 :
1#
#1070
0#
#1075
10
1,
0+
b100 9
b1001111010101010 F
b1001111010101010 K
b111000 N
b110 :
b1110001101010111000111 B
b101010101 ?
b101010101 P
1#
#1080
0#
#1085
b1010101 N
b10101010100000000000000 B
b100000000000000 A
b1000100010 C
b1000100010 I
b1000100010 J
0D
b1001111111111111 F
b1001111111111111 K
1+
1(
0,
00
b101 9
b10 E
b10 G
b10 H
b1001111010101010 !
b1001111010101010 )
b1001111010101010 ;
b1001111010101010 @
b1001111010101010 M
b100 :
1#
#1090
0#
#1095
b1000100010 A
1+
0(
b110 9
b1001111011111111 F
b1001111011111111 K
b0 N
b101 :
b1011010101001010 B
b1010101 ?
b1010101 P
1#
#1100
0#
#1105
b1001111010101010 F
b1001111010101010 K
10
1,
0+
b100 9
b0 B
b0 ?
b0 P
b110 :
1#
#1110
0#
#1115
b100000000000000 A
1+
1(
0,
00
b101 9
b1101 C
b1101 I
b1101 J
1D
b100 :
b11 E
b11 G
b11 H
1#
#1120
0#
#1125
b1101 A
1+
0(
b110 9
b101 :
1#
#1130
0#
#1135
10
1,
0+
b100 9
b110 :
1#
#1140
0#
#1145
b100000000000000 A
b0 C
b0 I
b0 J
0D
1+
1(
0,
00
b101 9
b100 E
b100 G
b100 H
b100 :
1#
#1150
0#
#1155
b0 A
1+
0(
b110 9
b101 :
1#
#1160
0#
#1165
10
1,
0+
b100 9
b110 :
1#
#1170
0#
#1175
b100000000000000 A
1+
1(
0,
00
b101 9
1D
b100 :
b101 E
b101 G
b101 H
1#
#1180
0#
#1185
b0 A
1+
0(
b110 9
b101 :
1#
#1190
0#
#1195
10
1,
0+
b100 9
b110 :
1#
#1200
0#
#1205
b100000000000000 A
0D
1+
1(
0,
00
b101 9
b110 E
b110 G
b110 H
b100 :
1#
#1210
0#
#1215
b0 A
1+
0(
b110 9
b101 :
1#
#1220
0#
#1225
10
1,
0+
b100 9
b110 :
1#
#1230
0#
#1235
b100000000000000 A
11
1+
1(
0,
00
b101 9
1D
b100 :
b111 E
b111 G
b111 H
1#
#1240
0#
#1245
b0 A
1+
0(
b110 9
b101 :
1#
#1250
0#
#1255
10
1,
0+
b0 9
b110 :
1#
#1260
0#
#1265
b1111111111111111 A
01
b1111111111111111 C
b1111111111111111 I
b1111111111111111 J
0D
1"
0,
00
b0 E
b0 G
b0 H
b0 :
1#
#1270
0#
#1275
1#
#1280
0#
#1285
1#
#1290
0#
#1295
1#
#1300
0#
#1305
b0 F
b0 K
b0 =
b0 L
b0 >
b0 O
b0 S
b0 !
b0 )
b0 ;
b0 @
b0 M
1#
1$
#1310
0#
#1315
b1 :
1#
b1 9
0"
1%
b1111111111111111 &
b1111111111111111 '
b1111111111111111 <
b1111111111111111 Q
0$
#1320
0#
#1325
1*
b10 :
1#
b11 9
0%
#1330
0#
#1335
1/
1.
1-
0*
b100 9
b11111111111111100000000000000001 =
b1111111111111111 L
b1111111111111111 >
b1111111111111111 O
b1111111111111111 S
b11 :
1#
#1340
0#
#1345
b1111111111111110 A
1+
1(
0-
0.
0/
b101 9
b11111111111111110 F
b11111111111111110 K
b1111111111111101 N
b100 :
b1111111111111111 !
b1111111111111111 )
b1111111111111111 ;
b1111111111111111 @
b1111111111111111 M
b11111111111111010000000000000010 B
b1111111111111111 ?
b1111111111111111 P
1#
#1350
0#
#1355
b1111111111111111 A
b11111111111111100 F
b11111111111111100 K
b1111111111111100 N
1+
0(
b110 9
b11111111111111000000000000000011 B
b1111111111111101 ?
b1111111111111101 P
b101 :
1#
#1360
0#
#1365
10
1,
0+
b100 9
b11111111111111011 F
b11111111111111011 K
b1111111111111011 N
b110 :
b11111111111110110000000000000100 B
b1111111111111100 ?
b1111111111111100 P
1#
#1370
0#
#1375
b1111111111111010 N
b11111111111110100000000000001000 B
b1111111111111110 A
b10101010101011 C
b10101010101011 I
b10101010101011 J
1D
b1111111111111111 F
b1111111111111111 K
1+
1(
0,
00
b101 9
b1 E
b1 G
b1 H
b11111111111111011 !
b11111111111111011 )
b11111111111111011 ;
b11111111111111011 @
b11111111111111011 M
b100 :
1#
#1380
0#
#1385
b10101010101011 A
1+
0(
b110 9
b10000000000000001 F
b10000000000000001 K
b10101010101001 N
b101 :
b101010101010011111111111111110 B
b1111111111111010 ?
b1111111111111010 P
1#
#1390
0#
#1395
b11101010101010010 F
b11101010101010010 K
b11100011100 N
10
1,
0+
b100 9
b111000111000011100011100011 B
b10101010101001 ?
b10101010101001 P
b110 :
1#
#1400
0#
#1405
b10101010101000 N
b101010101010001010101010101110 B
b1111111111111110 A
1+
1(
0,
00
b101 9
b11111111111111011 F
b11111111111111011 K
b1000100010 C
b1000100010 I
b1000100010 J
0D
b100 :
b11101010101010010 !
b11101010101010010 )
b11101010101010010 ;
b11101010101010010 @
b11101010101010010 M
b10 E
b10 G
b10 H
1#
#1410
0#
#1415
b1000100010 A
b11111111111111010 F
b11111111111111010 K
b1011010 N
1+
0(
b110 9
b10110101111101001010000 B
b10101010101000 ?
b10101010101000 P
b101 :
1#
#1420
0#
#1425
10
1,
0+
b100 9
b11101010110101100 F
b11101010110101100 K
b0 N
b110 :
b1011111111110100 B
b1011010 ?
b1011010 P
1#
#1430
0#
#1435
b1011001 N
b10110011111111101001100 B
b1111111111111110 A
b1101 C
b1101 I
b1101 J
1D
b11101010101010010 F
b11101010101010010 K
1+
1(
0,
00
b101 9
b11 E
b11 G
b11 H
b11101010110101100 !
b11101010110101100 )
b11101010110101100 ;
b11101010110101100 @
b11101010110101100 M
b100 :
1#
#1440
0#
#1445
b1101 A
1+
0(
b110 9
b11101010101010011 F
b11101010101010011 K
b0 N
b101 :
b10010000101 B
b1011001 ?
b1011001 P
1#
#1450
0#
#1455
b11101010110101100 F
b11101010110101100 K
10
1,
0+
b100 9
b0 B
b0 ?
b0 P
b110 :
1#
#1460
0#
#1465
b1111111111111110 A
1+
1(
0,
00
b101 9
b0 C
b0 I
b0 J
0D
b100 :
b100 E
b100 G
b100 H
1#
#1470
0#
#1475
b0 A
1+
0(
b110 9
b101 :
1#
#1480
0#
#1485
10
1,
0+
b100 9
b110 :
1#
#1490
0#
#1495
b1111111111111110 A
1D
1+
1(
0,
00
b101 9
b101 E
b101 G
b101 H
b100 :
1#
#1500
0#
#1505
b0 A
1+
0(
b110 9
b101 :
1#
#1510
0#
#1515
10
1,
0+
b100 9
b110 :
1#
#1520
0#
