sin.v
// Sin Module

`timescale 1ns/1ps

// --------------------------
// nBitReg: n–bit register with parameterized initial value
// --------------------------
module nBitReg #(
  parameter n = 16,
  parameter [n-1:0] INIT_VALUE = {n{1'b0}}
) (
  input                clk,
  input                rst,
  input                init,  // load constant INIT_VALUE
  input                load,  // load new value from 'in'
  input  [n - 1:0]     in,
  output reg [n - 1:0] out
);
  always @(posedge clk or posedge rst)
    if (rst)
      out <= 0;
    else if (init)
      out <= INIT_VALUE;
    else if (load)
      out <= in;
endmodule

// --------------------------
// cntReg: m–bit counter (used to count iterations)
// --------------------------
module cntReg #(
  parameter m = 3
) (
  input              clk,
  input              rst,
  input              cntUp,
  input              init0,
  output reg [m - 1:0] cnt
);
  always @(posedge clk or posedge rst)
    if (rst)
      cnt <= 0;
    else if (init0)
      cnt <= 0;
    else if (cntUp)
      cnt <= cnt + 1;
endmodule

// --------------------------
// sineLUT: Contains reciprocal factorial coefficients for sin(x)
// (The LUT coefficients assume fixed–point Q16 representation.)
//  address 0: 1/3! ≈ 0.16666 (16'h2AAA)
//  address 1: 1/5! ≈ 0.0083333 (16'h0222)
//  address 2: 1/7! ≈ 0.00019841 (16'h000D)
//  addresses 3–7: 0
// --------------------------
module sineLUT (
  input  [2:0] addr,
  output [15:0] out
);
  reg [15:0] dataOut;
  always @(*) begin
    case(addr)
      3'd0: dataOut = 16'h2AAA; // ~0.16666...
      3'd1: dataOut = 16'h0222; // ~0.008333...
      3'd2: dataOut = 16'h000D; // ~0.000198...
      default: dataOut = 16'h0000;
    endcase
  end
  assign out = dataOut;
endmodule

// --------------------------
// sineDataPathUnit: Implements the sine series evaluation
// Series: sin(x) = x - x^3/3! + x^5/5! - x^7/7! + ...
//
// It uses a two‐step update per term:
//    (a) Multiply the previous term by x^2.
//    (b) Multiply that result by the LUT coefficient (i.e. 1/((2n+2)(2n+3))).
//
// Two muxes are used:
//    - For tReg input: if initTsel is high, load x; else load the multiplication result.
//    - For sine accumulator: if initSsel is high, load {2'b0,x}; else load the adder output.
// --------------------------
module sineDataPathUnit (
    input         clk,
    input         rst,
    input         cntUp,
    input         init0,
    input         ldX,
    input         ldT,
    input         ldSine,
    input         selXorI,    // selects multiplier input: 1 selects x^2, 0 selects LUT
    input         sub,        // if asserted, subtract the term; else add
    input         initTsel,   // when high, load tReg with x from xReg
    input         initSsel,   // when high, load sineReg with {2'b0,x} (extended x)
    input  [15:0] xBus,
    output        cnt8,
    output [17:0] rBus
);
    wire [2:0] cntOut;
    wire [17:0] sineOut;
    wire [15:0] lutOut, xOut, tOut, muxOut;
    wire [31:0] multResult;
    wire [15:0] multOut;

    // Counter instance
    cntReg #(3) cntr (
        .clk(clk), .rst(rst), .cntUp(cntUp), .init0(init0), .cnt(cntOut)
    );
    
    // LUT for sine coefficients
    sineLUT lut (
        .addr(cntOut), .out(lutOut)
    );
    
    // x register: holds the input x value
    nBitReg #(16) xReg (
        .clk(clk), .rst(rst), .init(1'b0), .load(ldX),
        .in(xBus), .out(xOut)
    );
    
    // Compute x^2 (combinationally; take the upper 16 bits of the Q32 product)
    wire [31:0] xSq_full = xBus * xBus;
    wire [15:0] xSq = xSq_full[31:16];

    // tReg input multiplexer: if initTsel is high, use xOut; else use multOut.
    wire [15:0] t_in = (initTsel) ? xOut : multOut;
    // Term register: holds the current term in the series.
    nBitReg #(16) tReg (
        .clk(clk), .rst(rst), .init(1'b0), .load(ldT),
        .in(t_in), .out(tOut)
    );
    
    // Sine accumulator multiplexer: if initSsel is high, load {2'b0, xOut}; else use adder output.
    wire [17:0] sine_in = (initSsel) ? {2'b0, xOut} : addOut;
    // Sine accumulator register (18-bit)
    nBitReg #(18) sineReg (
        .clk(clk), .rst(rst), .init(1'b0), .load(ldSine),
        .in(sine_in), .out(sineOut)
    );
    
    // Multiplier input multiplexer: if selXorI is high, select x^2; else select LUT coefficient.
    assign muxOut = (selXorI) ? xSq : lutOut;
    
    // Multiply the current term (tOut) by the selected multiplier.
    assign multResult = tOut * muxOut;
    assign multOut = multResult[31:16];

    // Compute the new accumulator value:
    // Extend tOut to 18 bits and add (or subtract) it from the current sine accumulator.
    wire signed [17:0] termExtended = sub ? -{{2{tOut[15]}}, tOut} : {{2{tOut[15]}}, tOut};
    wire signed [17:0] sSineOut = sineOut;  // treat sine accumulator as signed
    wire signed [18:0] fullAdd = { sSineOut[17], sSineOut } + { termExtended[17], termExtended };
    wire signed [17:0] addOut =
        (fullAdd < 0) ? 18'd0 :
        (fullAdd > 18'd131071) ? 18'd131071 :
        fullAdd[17:0];

    assign cnt8 = (cntOut == 3'd7);
    assign rBus = sineOut;
endmodule

// --------------------------
// sineControlUnit: State machine for sin(x)
// States:
//   IDLE:   Waiting for start
//   INIT:   Load registers with x (and reset counter)
//   ITERATE1: Multiply previous term by x^2
//   ITERATE2: Multiply result by LUT coefficient
//   SINE:   Update accumulator with computed term and increment counter
//   DONE:   Finished series evaluation
// --------------------------
module sineControlUnit (
  input  clk,
  input  rst,
  input  start,
  input  cnt8,
  output reg ldX,
  output reg ldT,
  output reg initTsel,   // when high, load tReg with x from xReg
  output reg initSsel,   // when high, load sineReg with {2'b0,x}
  output reg init0,
  output reg ldSine,
  output reg selXorI,
  output reg cntUp,
  output reg done,
  output reg sub
);
  parameter [2:0]
    IDLE     = 3'd0,
    INIT     = 3'd1,
    ITERATE1 = 3'd2,
    ITERATE2 = 3'd3,
    SINE     = 3'd4,
    DONE     = 3'd5;
    
  reg [2:0] state, next;
  // sign flag: 1 means subtract the term; 0 means add.
  // (For sin(x), the first computed term should be subtracted.)
  reg sign;

  // State register and sign toggling.
  always @(posedge clk or posedge rst) begin
    if (rst) begin
      state <= IDLE;
      sign  <= 1'b1;
    end else begin
      state <= next;
      if (state == SINE)
        sign <= ~sign;
    end
  end

  // Next-state and output logic.
  always @(*) begin
    // Default all control signals to 0.
    next      = state;
    ldX       = 0;
    ldT       = 0;
    initTsel  = 0;
    initSsel  = 0;
    init0     = 0;
    ldSine    = 0;
    selXorI   = 0;
    cntUp     = 0;
    done      = 0;
    sub       = 0;
    
    case (state)
      IDLE: begin
        if (start)
          next = INIT;
      end
      INIT: begin
        // Load x into xReg, tReg, and sineReg, and reset counter.
        ldX       = 1;
        ldT       = 1;       // Load tReg with x.
        ldSine    = 1;       // Load sineReg with x.
        initTsel  = 1;       // Select x for tReg.
        initSsel  = 1;       // Select {2'b0,x} for sineReg.
        init0     = 1;       // Reset counter.
        next = ITERATE1;
      end
      ITERATE1: begin
        // Multiply previous term by x^2.
        selXorI = 1;  // Select x^2.
        ldT     = 1;  // Update tReg.
        next    = ITERATE2;
      end
      ITERATE2: begin
        // Multiply the result by the LUT coefficient.
        selXorI = 0;  // Select LUT coefficient.
        ldT     = 1;  // Update tReg.
        next    = SINE;
      end
      SINE: begin
        // Update the sine accumulator with the computed term (adding or subtracting).
        ldSine = 1;
        cntUp  = 1;
        sub    = sign;  // Use current sign flag.
        if (cnt8)
          next = DONE;
        else
          next = ITERATE1;
      end
      DONE: begin
        done = 1;
        if (~start)
          next = IDLE;
      end
      default: next = IDLE;
    endcase
  end
endmodule

// --------------------------
// sineTop: Top-level module for sin(x)
// --------------------------
module sineTop (
  input         clk,
  input         rst,
  input         start,
  input  [15:0] xBus,
  output [17:0] rBus,
  output        done
);
  wire ldX, ldT, initTsel, initSsel, init0, ldSine, selXorI, cntUp, cnt8, sub;

  sineControlUnit sineControl (
    .clk(clk), .rst(rst), .start(start), .cnt8(cnt8),
    .ldX(ldX), .ldT(ldT), .initTsel(initTsel), .initSsel(initSsel),
    .init0(init0), .ldSine(ldSine), .selXorI(selXorI),
    .cntUp(cntUp), .done(done), .sub(sub)
  );

  sineDataPathUnit sineDataPath (
    .clk(clk), .rst(rst), .cntUp(cntUp), .init0(init0),
    .ldX(ldX), .ldT(ldT), .ldSine(ldSine),
    .selXorI(selXorI), .sub(sub),
    .initTsel(initTsel), .initSsel(initSsel),
    .xBus(xBus), .cnt8(cnt8), .rBus(rBus)
  );
endmodule

cosTB.v

`timescale 1ns/1ps

module sineTop_tb;
  reg         clk, rst, start;
  reg  [15:0] xBus;
  wire [17:0] rBus;
  wire        done;

  // Instantiate the sineTop module
  sineTop dut (
    .clk(clk),
    .rst(rst),
    .start(start),
    .xBus(xBus),
    .rBus(rBus),
    .done(done)
  );

  // Clock generation: 10 ns period
  always #5 clk = ~clk;

  initial begin
    clk   = 0;
    rst   = 1;
    start = 0;
    xBus  = 16'h1000; // Example input (0.0625 in fixed-point)

    // Dump waveform data to a file
    $dumpfile("sine_test.vcd"); // Specify the output file
    $dumpvars(0, sineTop_tb);    // Dump all variables in the testbench

    #10 rst = 0;    // Release reset
    #10 start = 1;  // Start the computation
    #10 start = 0;  // Deassert start

    wait(done);    // Wait for the computation to finish
    $display("sine(0.0625) = 0x%h", rBus);

    #20 $finish;
  end
endmodule

sine_test.vcd
$date
	Wed Feb  5 20:33:54 2025
$end
$version
	Icarus Verilog
$end
$timescale
	1ps
$end
$scope module sineTop_tb $end
$var wire 18 ! rBus [17:0] $end
$var wire 1 " done $end
$var reg 1 # clk $end
$var reg 1 $ rst $end
$var reg 1 % start $end
$var reg 16 & xBus [15:0] $end
$scope module dut $end
$var wire 1 # clk $end
$var wire 1 $ rst $end
$var wire 1 % start $end
$var wire 16 ' xBus [15:0] $end
$var wire 1 ( sub $end
$var wire 1 ) selXorI $end
$var wire 18 * rBus [17:0] $end
$var wire 1 + ldX $end
$var wire 1 , ldT $end
$var wire 1 - ldSine $end
$var wire 1 . initTsel $end
$var wire 1 / initSsel $end
$var wire 1 0 init0 $end
$var wire 1 " done $end
$var wire 1 1 cntUp $end
$var wire 1 2 cnt8 $end
$scope module sineControl $end
$var wire 1 # clk $end
$var wire 1 $ rst $end
$var wire 1 % start $end
$var wire 1 2 cnt8 $end
$var parameter 3 3 DONE $end
$var parameter 3 4 IDLE $end
$var parameter 3 5 INIT $end
$var parameter 3 6 ITERATE1 $end
$var parameter 3 7 ITERATE2 $end
$var parameter 3 8 SINE $end
$var reg 1 1 cntUp $end
$var reg 1 " done $end
$var reg 1 0 init0 $end
$var reg 1 / initSsel $end
$var reg 1 . initTsel $end
$var reg 1 - ldSine $end
$var reg 1 , ldT $end
$var reg 1 + ldX $end
$var reg 3 9 next [2:0] $end
$var reg 1 ) selXorI $end
$var reg 1 : sign $end
$var reg 3 ; state [2:0] $end
$var reg 1 ( sub $end
$upscope $end
$scope module sineDataPath $end
$var wire 1 # clk $end
$var wire 1 1 cntUp $end
$var wire 1 0 init0 $end
$var wire 1 / initSsel $end
$var wire 1 . initTsel $end
$var wire 1 - ldSine $end
$var wire 1 , ldT $end
$var wire 1 + ldX $end
$var wire 18 < rBus [17:0] $end
$var wire 1 $ rst $end
$var wire 18 = sSineOut [17:0] $end
$var wire 1 ) selXorI $end
$var wire 1 ( sub $end
$var wire 16 > xBus [15:0] $end
$var wire 32 ? xSq_full [31:0] $end
$var wire 16 @ xSq [15:0] $end
$var wire 16 A xOut [15:0] $end
$var wire 18 B termExtended [17:0] $end
$var wire 16 C t_in [15:0] $end
$var wire 16 D tOut [15:0] $end
$var wire 18 E sine_in [17:0] $end
$var wire 18 F sineOut [17:0] $end
$var wire 16 G muxOut [15:0] $end
$var wire 32 H multResult [31:0] $end
$var wire 16 I multOut [15:0] $end
$var wire 16 J lutOut [15:0] $end
$var wire 19 K fullAdd [18:0] $end
$var wire 3 L cntOut [2:0] $end
$var wire 1 2 cnt8 $end
$var wire 18 M addOut [17:0] $end
$scope module cntr $end
$var wire 1 # clk $end
$var wire 1 1 cntUp $end
$var wire 1 0 init0 $end
$var wire 1 $ rst $end
$var parameter 32 N m $end
$var reg 3 O cnt [2:0] $end
$upscope $end
$scope module lut $end
$var wire 3 P addr [2:0] $end
$var wire 16 Q out [15:0] $end
$var reg 16 R dataOut [15:0] $end
$upscope $end
$scope module sineReg $end
$var wire 1 # clk $end
$var wire 18 S in [17:0] $end
$var wire 1 T init $end
$var wire 1 - load $end
$var wire 1 $ rst $end
$var parameter 18 U INIT_VALUE $end
$var parameter 32 V n $end
$var reg 18 W out [17:0] $end
$upscope $end
$scope module tReg $end
$var wire 1 # clk $end
$var wire 16 X in [15:0] $end
$var wire 1 Y init $end
$var wire 1 , load $end
$var wire 1 $ rst $end
$var parameter 16 Z INIT_VALUE $end
$var parameter 32 [ n $end
$var reg 16 \ out [15:0] $end
$upscope $end
$scope module xReg $end
$var wire 1 # clk $end
$var wire 16 ] in [15:0] $end
$var wire 1 ^ init $end
$var wire 1 + load $end
$var wire 1 $ rst $end
$var parameter 16 _ INIT_VALUE $end
$var parameter 32 ` n $end
$var reg 16 a out [15:0] $end
$upscope $end
$upscope $end
$upscope $end
$upscope $end
$enddefinitions $end
$comment Show the parameter values. $end
$dumpall
b10000 `
b0 _
b10000 [
b0 Z
b10010 V
b0 U
b11 N
b100 8
b11 7
b10 6
b1 5
b0 4
b101 3
$end
#0
$dumpvars
b0 a
0^
b1000000000000 ]
b0 \
0Y
b0 X
b0 W
0T
b0 S
b10101010101010 R
b10101010101010 Q
b0 P
b0 O
b0 M
b0 L
b0 K
b10101010101010 J
b0 I
b0 H
b10101010101010 G
b0 F
b0 E
b0 D
b0 C
b0 B
b0 A
b100000000 @
b1000000000000000000000000 ?
b1000000000000 >
b0 =
b0 <
b0 ;
1:
b0 9
02
01
00
0/
0.
0-
0,
0+
b0 *
0)
0(
b1000000000000 '
b1000000000000 &
0%
1$
0#
0"
b0 !
$end
#5000
1#
#10000
0#
0$
#15000
1#
#20000
b1 9
0#
1%
#25000
b10 9
10
1/
1.
1-
1,
1+
b1 ;
1#
#30000
1-
10
1/
1.
1,
1+
b10 9
0#
0%
#35000
b100000000 G
b11 9
1)
0-
00
0/
0.
1,
0+
b0 E
b0 S
b0 C
b0 X
b10 ;
b1000000000000 A
b1000000000000 a
1#
#40000
0#
#45000
b10101010101010 G
b100 9
0)
1,
b11 ;
1#
#50000
0#
#55000
b10 9
1(
11
1-
0,
b100 ;
1#
#60000
0#
#65000
b100000000 G
b1000100010 J
b1000100010 Q
b1000100010 R
b11 9
1,
1)
0(
01
0-
b1 L
b1 O
b1 P
0:
b10 ;
1#
#70000
0#
#75000
b1000100010 G
b100 9
0)
1,
b11 ;
1#
#80000
0#
#85000
b10 9
11
1-
0,
b100 ;
1#
#90000
0#
#95000
b100000000 G
b11 9
1,
1)
01
0-
b1101 J
b1101 Q
b1101 R
1:
b10 ;
b10 L
b10 O
b10 P
1#
#100000
0#
#105000
b1101 G
b100 9
0)
1,
b11 ;
1#
#110000
0#
#115000
b10 9
1(
11
1-
0,
b100 ;
1#
#120000
0#
#125000
b100000000 G
b0 J
b0 Q
b0 R
b11 9
1,
1)
0(
01
0-
b11 L
b11 O
b11 P
0:
b10 ;
1#
#130000
0#
#135000
b0 G
b100 9
0)
1,
b11 ;
1#
#140000
0#
#145000
b10 9
11
1-
0,
b100 ;
1#
#150000
0#
#155000
b100000000 G
b11 9
1,
1)
01
0-
1:
b10 ;
b100 L
b100 O
b100 P
1#
#160000
0#
#165000
b0 G
b100 9
0)
1,
b11 ;
1#
#170000
0#
#175000
b10 9
1(
11
1-
0,
b100 ;
1#
#180000
0#
#185000
b100000000 G
b11 9
1,
1)
0(
01
0-
b101 L
b101 O
b101 P
0:
b10 ;
1#
#190000
0#
#195000
b0 G
b100 9
0)
1,
b11 ;
1#
#200000
0#
#205000
b10 9
11
1-
0,
b100 ;
1#
#210000
0#
#215000
b100000000 G
b11 9
1,
1)
01
0-
1:
b10 ;
b110 L
b110 O
b110 P
1#
#220000
0#
#225000
b0 G
b100 9
0)
1,
b11 ;
1#
#230000
0#
#235000
b10 9
1(
11
1-
0,
b100 ;
1#
#240000
0#
#245000
b100000000 G
b11 9
1,
1)
0(
01
0-
12
b111 L
b111 O
b111 P
0:
b10 ;
1#
#250000
0#
#255000
b0 G
b100 9
0)
1,
b11 ;
1#
#260000
0#
#265000
b101 9
11
1-
0,
b100 ;
1#
#270000
0#
#275000
b10101010101010 G
b10101010101010 J
b10101010101010 Q
b10101010101010 R
b0 9
1"
01
0-
1:
b101 ;
02
b0 L
b0 O
b0 P
1#
#280000
0#
#285000
0"
b0 ;
1#
